Workbook

Sheet WorkSheet_ANS
A1: OrderID | B1: Date | C1: Year | D1: Month | E1: CustomerName | F1: Region | G1: Country | H1: City | I1: ProductCategory | J1: ProductName | K1: SalesChannel | L1: SalesRep | M1: UnitPrice | N1: Quantity | O1: Discount | P1: DiscountType | Q1: Revenue | R1: OrderType | S1: PremiumOrder | T1: Cost | U1: Profit | V1: PaymentMethod | W1: OrderPriority | X1: ShipMode | Y1: ShippingCost | Z1: DeliveryDays | AA1: DeliveryType | AB1: CustomerSegment | AC1: Returned | AD1: Rating | AE1: ProductReview | AF1: SaleValue | AG1: Profit Margin | AQ1: Count total number of orders. | AY1: =COUNTA(WorkSheet_ANS!$A$1:$A$999) -> 999 | BC1: Count orders per Month.AND Calculate Revenue per Month.
A2: 1 | B2: 2023-08-26 | C2: =YEAR(Table2[[#This Row],[Date]]) -> 2023 | D2: =TEXT(Table2[[#This Row],[Date]],"mmmm") -> August | E2: Michael | F2: North | G2: Canada | H2: Mumbai | I2: Electronics | J2: Jacket | K2: Retail | L2: Rep D | M2: 576.66 | N2: 4 | O2: 0.17 | P2: =IF(Table2[[#This Row],[Discount]]>20%,"HIGH","LOW") -> LOW | Q2: 1914.51 | R2: =_xlfn.IFS(Table2[[#This Row],[Revenue]]<1000,"Small",OR(Table2[[#This Row],[Revenue]]>1000,Table2[[#This Row],[Revenue]]<=5000),"Medium",Table2[[#This Row],[Revenue]]>5000,"Large") -> Medium | S2: =IF(Table2[[#This Row],[Revenue]]>3000,"Premium","Not Premium") -> Not Premium | T2: 1118.63 | U2: 795.88 | V2: Bank Transfer | W2: Medium | X2: Standard | Y2: 32.48 | Z2: 10 | AA2: =IF(Table2[[#This Row],[DeliveryDays]]<=3,"FAST DELIVERY","LATE DELIVERY") -> LATE DELIVERY | AB2: Home Office | AC2: No | AD2: 2 | AE2: =_xlfn.IFS(Table2[[#This Row],[Rating]]=5,"Excellent",Table2[[#This Row],[Rating]]=4,"Good",Table2[[#This Row],[Rating]]=3,"Average",Table2[[#This Row],[Rating]]<=2,"Poor") -> Poor | AF2: =Table2[[#This Row],[Cost]]+Table2[[#This Row],[Profit]]+Table2[[#This Row],[ShippingCost]]+Table2[[#This Row],[DeliveryDays]] -> 1956.99 | AG2: =Table2[[#This Row],[Profit]]/Table2[[#This Row],[Cost]] -> 0.71147743 | BC2: Month | BD2: Orders | BE2: Revenue | BF2: SalesValue | BG2: Profit | BH2: GrowthRate
A3: 2 | B3: 2024-10-15 | C3: =YEAR(Table2[[#This Row],[Date]]) -> 2024 | D3: =TEXT(Table2[[#This Row],[Date]],"mmmm") -> October | E3: Priya | F3: South | G3: USA | H3: Berlin | I3: Electronics | J3: Jacket | K3: Online | L3: Rep C | M3: 447.27 | N3: 5 | O3: 0.12 | P3: =IF(Table2[[#This Row],[Discount]]>20%,"HIGH","LOW") -> LOW | Q3: 1967.99 | R3: =_xlfn.IFS(Table2[[#This Row],[Revenue]]<1000,"Small",OR(Table2[[#This Row],[Revenue]]>1000,Table2[[#This Row],[Revenue]]<=5000),"Medium",Table2[[#This Row],[Revenue]]>5000,"Large") -> Medium | S3: =IF(Table2[[#This Row],[Revenue]]>3000,"Premium","Not Premium") -> Not Premium | T3: 1337.43 | U3: 630.56 | V3: Credit Card | W3: Medium | X3: Same Day | Y3: 25.58 | Z3: 4 | AA3: =IF(Table2[[#This Row],[DeliveryDays]]<=3,"FAST DELIVERY","LATE DELIVERY") -> LATE DELIVERY | AB3: Home Office | AC3: No | AD3: 1 | AE3: =_xlfn.IFS(Table2[[#This Row],[Rating]]=5,"Excellent",Table2[[#This Row],[Rating]]=4,"Good",Table2[[#This Row],[Rating]]=3,"Average",Table2[[#This Row],[Rating]]<=2,"Poor") -> Poor | AF3: =Table2[[#This Row],[Cost]]+Table2[[#This Row],[Profit]]+Table2[[#This Row],[ShippingCost]]+Table2[[#This Row],[DeliveryDays]] -> 1997.57 | AG3: =Table2[[#This Row],[Profit]]/Table2[[#This Row],[Cost]] -> 0.4714714 | AQ3: Count how many customers appear in the dataset. | AY3: =COUNTA(WorkSheet_ANS!$E$1:$E$999) -> 999 | BC3: January | BD3: =COUNTIF(Table2[[#All],[Month]],$BC3) -> 72 | BE3: =SUMIF(Table2[Month],BC3,Table2[Revenue]) -> 305092.44 | BF3: =SUMIF(Table2[[#All],[Month]],BC3,Table2[[#All],[SaleValue]]) -> 307506.98 | BG3: =SUMIF(Table2[[#All],[Month]],BC3,Table2[[#All],[Profit]]) -> 97799.52 | BH3: 0
A4: 3 | B4: 2024-12-04 | C4: =YEAR(Table2[[#This Row],[Date]]) -> 2024 | D4: =TEXT(Table2[[#This Row],[Date]],"mmmm") -> December | E4: David | F4: North | G4: USA | H4: Mumbai | I4: Sports | J4: Keyboard | K4: Distributor | L4: Rep C | M4: 344.45 | N4: 19 | O4: 0.15 | P4: =IF(Table2[[#This Row],[Discount]]>20%,"HIGH","LOW") -> LOW | Q4: 5562.87 | R4: =_xlfn.IFS(Table2[[#This Row],[Revenue]]<1000,"Small",OR(Table2[[#This Row],[Revenue]]>1000,Table2[[#This Row],[Revenue]]<=5000),"Medium",Table2[[#This Row],[Revenue]]>5000,"Large") -> Medium | S4: =IF(Table2[[#This Row],[Revenue]]>3000,"Premium","Not Premium") -> Premium | T4: 4009.72 | U4: 1553.15 | V4: Credit Card | W4: Critical | X4: Standard | Y4: 27.68 | Z4: 1 | AA4: =IF(Table2[[#This Row],[DeliveryDays]]<=3,"FAST DELIVERY","LATE DELIVERY") -> FAST DELIVERY | AB4: Corporate | AC4: Yes | AD4: 1 | AE4: =_xlfn.IFS(Table2[[#This Row],[Rating]]=5,"Excellent",Table2[[#This Row],[Rating]]=4,"Good",Table2[[#This Row],[Rating]]=3,"Average",Table2[[#This Row],[Rating]]<=2,"Poor") -> Poor | AF4: =Table2[[#This Row],[Cost]]+Table2[[#This Row],[Profit]]+Table2[[#This Row],[ShippingCost]]+Table2[[#This Row],[DeliveryDays]] -> 5591.55 | AG4: =Table2[[#This Row],[Profit]]/Table2[[#This Row],[Cost]] -> 0.38734625 | BC4: February | BD4: =COUNTIF(Table2[[#All],[Month]],$BC4) -> 68 | BE4: =SUMIF(Table2[Month],BC4,Table2[Revenue]) -> 324240.36 | BF4: =SUMIF(Table2[[#All],[Month]],BC4,Table2[[#All],[SaleValue]]) -> 326483.54 | BG4: =SUMIF(Table2[[#All],[Month]],BC4,Table2[[#All],[Profit]]) -> 95325.45 | BH4: =(BE4-BE3)/BE3 -> 0.062761044
A5: 4 | B5: 2023-01-07 | C5: =YEAR(Table2[[#This Row],[Date]]) -> 2023 | D5: =TEXT(Table2[[#This Row],[Date]],"mmmm") -> January | E5: Riya | F5: South | G5: India | H5: Sydney | I5: Furniture | J5: Chair | K5: Retail | L5: Rep D | M5: 438.12 | N5: 16 | O5: 0.28 | P5: =IF(Table2[[#This Row],[Discount]]>20%,"HIGH","LOW") -> HIGH | Q5: 5047.14 | R5: =_xlfn.IFS(Table2[[#This Row],[Revenue]]<1000,"Small",OR(Table2[[#This Row],[Revenue]]>1000,Table2[[#This Row],[Revenue]]<=5000),"Medium",Table2[[#This Row],[Revenue]]>5000,"Large") -> Medium | S5: =IF(Table2[[#This Row],[Revenue]]>3000,"Premium","Not Premium") -> Premium | T5: 2684.67 | U5: 2362.47 | V5: PayPal | W5: Critical | X5: Same Day | Y5: 23.41 | Z5: 3 | AA5: =IF(Table2[[#This Row],[DeliveryDays]]<=3,"FAST DELIVERY","LATE DELIVERY") -> FAST DELIVERY | AB5: Home Office | AC5: Yes | AD5: 1 | AE5: =_xlfn.IFS(Table2[[#This Row],[Rating]]=5,"Excellent",Table2[[#This Row],[Rating]]=4,"Good",Table2[[#This Row],[Rating]]=3,"Average",Table2[[#This Row],[Rating]]<=2,"Poor") -> Poor | AF5: =Table2[[#This Row],[Cost]]+Table2[[#This Row],[Profit]]+Table2[[#This Row],[ShippingCost]]+Table2[[#This Row],[DeliveryDays]] -> 5073.55 | AG5: =Table2[[#This Row],[Profit]]/Table2[[#This Row],[Cost]] -> 0.87998525 | AQ5: Count orders where Returned = Yes. | AY5: =COUNTIF(WorkSheet_ANS!$AC$1:$AC$999,"Yes") -> 499 | BC5: March | BD5: =COUNTIF(Table2[[#All],[Month]],$BC5) -> 89 | BE5: =SUMIF(Table2[Month],BC5,Table2[Revenue]) -> 345517.57 | BF5: =SUMIF(Table2[[#All],[Month]],BC5,Table2[[#All],[SaleValue]]) -> 348582.49 | BG5: =SUMIF(Table2[[#All],[Month]],BC5,Table2[[#All],[Profit]]) -> 111728.88 | BH5: =(BE5-BE4)/BE4 -> 0.06562172
A6: 5 | B6: 2024-05-25 | C6: =YEAR(Table2[[#This Row],[Date]]) -> 2024 | D6: =TEXT(Table2[[#This Row],[Date]],"mmmm") -> May | E6: Sophia | F6: East | G6: India | H6: Pune | I6: Office Supplies | J6: Desk | K6: Retail | L6: Rep A | M6: 80.22 | N6: 15 | O6: 0 | P6: =IF(Table2[[#This Row],[Discount]]>20%,"HIGH","LOW") -> LOW | Q6: 1203.3 | R6: =_xlfn.IFS(Table2[[#This Row],[Revenue]]<1000,"Small",OR(Table2[[#This Row],[Revenue]]>1000,Table2[[#This Row],[Revenue]]<=5000),"Medium",Table2[[#This Row],[Revenue]]>5000,"Large") -> Medium | S6: =IF(Table2[[#This Row],[Revenue]]>3000,"Premium","Not Premium") -> Not Premium | T6: 745.46 | U6: 457.84 | V6: Bank Transfer | W6: Low | X6: Express | Y6: 29.52 | Z6: 8 | AA6: =IF(Table2[[#This Row],[DeliveryDays]]<=3,"FAST DELIVERY","LATE DELIVERY") -> LATE DELIVERY | AB6: Home Office | AC6: Yes | AD6: 1 | AE6: =_xlfn.IFS(Table2[[#This Row],[Rating]]=5,"Excellent",Table2[[#This Row],[Rating]]=4,"Good",Table2[[#This Row],[Rating]]=3,"Average",Table2[[#This Row],[Rating]]<=2,"Poor") -> Poor | AF6: =Table2[[#This Row],[Cost]]+Table2[[#This Row],[Profit]]+Table2[[#This Row],[ShippingCost]]+Table2[[#This Row],[DeliveryDays]] -> 1240.82 | AG6: =Table2[[#This Row],[Profit]]/Table2[[#This Row],[Cost]] -> 0.61417112 | BC6: April | BD6: =COUNTIF(Table2[[#All],[Month]],$BC6) -> 78 | BE6: =SUMIF(Table2[Month],BC6,Table2[Revenue]) -> 245976.51 | BF6: =SUMIF(Table2[[#All],[Month]],BC6,Table2[[#All],[SaleValue]]) -> 248734.52 | BG6: =SUMIF(Table2[[#All],[Month]],BC6,Table2[[#All],[Profit]]) -> 71169.89 | BH6: =(BE6-BE5)/BE5 -> -0.28809261
A7: 6 | B7: 2023-05-07 | C7: =YEAR(Table2[[#This Row],[Date]]) -> 2023 | D7: =TEXT(Table2[[#This Row],[Date]],"mmmm") -> May | E7: Riya | F7: East | G7: India | H7: Delhi | I7: Clothing | J7: Jacket | K7: Distributor | L7: Rep A | M7: 956.16 | N7: 2 | O7: 0 | P7: =IF(Table2[[#This Row],[Discount]]>20%,"HIGH","LOW") -> LOW | Q7: 1912.32 | R7: =_xlfn.IFS(Table2[[#This Row],[Revenue]]<1000,"Small",OR(Table2[[#This Row],[Revenue]]>1000,Table2[[#This Row],[Revenue]]<=5000),"Medium",Table2[[#This Row],[Revenue]]>5000,"Large") -> Medium | S7: =IF(Table2[[#This Row],[Revenue]]>3000,"Premium","Not Premium") -> Not Premium | T7: 1376.98 | U7: 535.34 | V7: Cash | W7: Low | X7: Express | Y7: 7.77 | Z7: 2 | AA7: =IF(Table2[[#This Row],[DeliveryDays]]<=3,"FAST DELIVERY","LATE DELIVERY") -> FAST DELIVERY | AB7: Corporate | AC7: Yes | AD7: 4 | AE7: =_xlfn.IFS(Table2[[#This Row],[Rating]]=5,"Excellent",Table2[[#This Row],[Rating]]=4,"Good",Table2[[#This Row],[Rating]]=3,"Average",Table2[[#This Row],[Rating]]<=2,"Poor") -> Good | AF7: =Table2[[#This Row],[Cost]]+Table2[[#This Row],[Profit]]+Table2[[#This Row],[ShippingCost]]+Table2[[#This Row],[DeliveryDays]] -> 1922.09 | AG7: =Table2[[#This Row],[Profit]]/Table2[[#This Row],[Cost]] -> 0.38877834 | AQ7: Count orders where Returned = No. | AY7: =COUNTIF(WorkSheet_ANS!$AC$1:$AC$999,"No") -> 499 | BC7: May | BD7: =COUNTIF(Table2[[#All],[Month]],$BC7) -> 96 | BE7: =SUMIF(Table2[Month],BC7,Table2[Revenue]) -> 463426.5 | BF7: =SUMIF(Table2[[#All],[Month]],BC7,Table2[[#All],[SaleValue]]) -> 466286.82 | BG7: =SUMIF(Table2[[#All],[Month]],BC7,Table2[[#All],[Profit]]) -> 145553.43 | BH7: =(BE7-BE6)/BE6 -> 0.88402746
A8: 7 | B8: 2024-06-19 | C8: =YEAR(Table2[[#This Row],[Date]]) -> 2024 | D8: =TEXT(Table2[[#This Row],[Date]],"mmmm") -> June | E8: David | F8: East | G8: India | H8: New York | I8: Office Supplies | J8: Tablet | K8: Retail | L8: Rep B | M8: 342.02 | N8: 20 | O8: 0.08 | P8: =IF(Table2[[#This Row],[Discount]]>20%,"HIGH","LOW") -> LOW | Q8: 6293.17 | R8: =_xlfn.IFS(Table2[[#This Row],[Revenue]]<1000,"Small",OR(Table2[[#This Row],[Revenue]]>1000,Table2[[#This Row],[Revenue]]<=5000),"Medium",Table2[[#This Row],[Revenue]]>5000,"Large") -> Medium | S8: =IF(Table2[[#This Row],[Revenue]]>3000,"Premium","Not Premium") -> Premium | T8: 3483.81 | U8: 2809.36 | V8: Cash | W8: Low | X8: Standard | Y8: 32.24 | Z8: 2 | AA8: =IF(Table2[[#This Row],[DeliveryDays]]<=3,"FAST DELIVERY","LATE DELIVERY") -> FAST DELIVERY | AB8: Home Office | AC8: Yes | AD8: 3 | AE8: =_xlfn.IFS(Table2[[#This Row],[Rating]]=5,"Excellent",Table2[[#This Row],[Rating]]=4,"Good",Table2[[#This Row],[Rating]]=3,"Average",Table2[[#This Row],[Rating]]<=2,"Poor") -> Average | AF8: =Table2[[#This Row],[Cost]]+Table2[[#This Row],[Profit]]+Table2[[#This Row],[ShippingCost]]+Table2[[#This Row],[DeliveryDays]] -> 6327.41 | AG8: =Table2[[#This Row],[Profit]]/Table2[[#This Row],[Cost]] -> 0.80640448 | BC8: June | BD8: =COUNTIF(Table2[[#All],[Month]],$BC8) -> 91 | BE8: =SUMIF(Table2[Month],BC8,Table2[Revenue]) -> 323348.37 | BF8: =SUMIF(Table2[[#All],[Month]],BC8,Table2[[#All],[SaleValue]]) -> 326385.37 | BG8: =SUMIF(Table2[[#All],[Month]],BC8,Table2[[#All],[Profit]]) -> 93950.05 | BH8: =(BE8-BE7)/BE7 -> -0.30226612
A9: 8 | B9: 2024-09-25 | C9: =YEAR(Table2[[#This Row],[Date]]) -> 2024 | D9: =TEXT(Table2[[#This Row],[Date]],"mmmm") -> September | E9: Sophia | F9: West | G9: Germany | H9: Mumbai | I9: Furniture | J9: T-Shirt | K9: Retail | L9: Rep E | M9: 380.23 | N9: 5 | O9: 0.01 | P9: =IF(Table2[[#This Row],[Discount]]>20%,"HIGH","LOW") -> LOW | Q9: 1882.14 | R9: =_xlfn.IFS(Table2[[#This Row],[Revenue]]<1000,"Small",OR(Table2[[#This Row],[Revenue]]>1000,Table2[[#This Row],[Revenue]]<=5000),"Medium",Table2[[#This Row],[Revenue]]>5000,"Large") -> Medium | S9: =IF(Table2[[#This Row],[Revenue]]>3000,"Premium","Not Premium") -> Not Premium | T9: 1181.3 | U9: 700.84 | V9: Cash | W9: Medium | X9: Express | Y9: 28.33 | Z9: 4 | AA9: =IF(Table2[[#This Row],[DeliveryDays]]<=3,"FAST DELIVERY","LATE DELIVERY") -> LATE DELIVERY | AB9: Home Office | AC9: Yes | AD9: 2 | AE9: =_xlfn.IFS(Table2[[#This Row],[Rating]]=5,"Excellent",Table2[[#This Row],[Rating]]=4,"Good",Table2[[#This Row],[Rating]]=3,"Average",Table2[[#This Row],[Rating]]<=2,"Poor") -> Poor | AF9: =Table2[[#This Row],[Cost]]+Table2[[#This Row],[Profit]]+Table2[[#This Row],[ShippingCost]]+Table2[[#This Row],[DeliveryDays]] -> 1914.47 | AG9: =Table2[[#This Row],[Profit]]/Table2[[#This Row],[Cost]] -> 0.59327859 | AQ9: Find the average UnitPrice. | AY9: =AVERAGE(WorkSheet_ANS!$M$1:$M$999) -> 498.02772 | BC9: July | BD9: =COUNTIF(Table2[[#All],[Month]],$BC9) -> 92 | BE9: =SUMIF(Table2[Month],BC9,Table2[Revenue]) -> 478422.08 | BF9: =SUMIF(Table2[[#All],[Month]],BC9,Table2[[#All],[SaleValue]]) -> 481599.27 | BG9: =SUMIF(Table2[[#All],[Month]],BC9,Table2[[#All],[Profit]]) -> 139079.79 | BH9: =(BE9-BE8)/BE8 -> 0.47958711
A10: 9 | B10: 2023-07-24 | C10: =YEAR(Table2[[#This Row],[Date]]) -> 2023 | D10: =TEXT(Table2[[#This Row],[Date]],"mmmm") -> July | E10: Riya | F10: North | G10: Canada | H10: New York | I10: Furniture | J10: Football | K10: Online | L10: Rep D | M10: 604.76 | N10: 19 | O10: 0.18 | P10: =IF(Table2[[#This Row],[Discount]]>20%,"HIGH","LOW") -> LOW | Q10: 9422.16 | R10: =_xlfn.IFS(Table2[[#This Row],[Revenue]]<1000,"Small",OR(Table2[[#This Row],[Revenue]]>1000,Table2[[#This Row],[Revenue]]<=5000),"Medium",Table2[[#This Row],[Revenue]]>5000,"Large") -> Medium | S10: =IF(Table2[[#This Row],[Revenue]]>3000,"Premium","Not Premium") -> Premium | T10: 7639.72 | U10: 1782.44 | V10: Bank Transfer | W10: High | X10: Same Day | Y10: 29.33 | Z10: 8 | AA10: =IF(Table2[[#This Row],[DeliveryDays]]<=3,"FAST DELIVERY","LATE DELIVERY") -> LATE DELIVERY | AB10: Corporate | AC10: No | AD10: 3 | AE10: =_xlfn.IFS(Table2[[#This Row],[Rating]]=5,"Excellent",Table2[[#This Row],[Rating]]=4,"Good",Table2[[#This Row],[Rating]]=3,"Average",Table2[[#This Row],[Rating]]<=2,"Poor") -> Average | AF10: =Table2[[#This Row],[Cost]]+Table2[[#This Row],[Profit]]+Table2[[#This Row],[ShippingCost]]+Table2[[#This Row],[DeliveryDays]] -> 9459.49 | AG10: =Table2[[#This Row],[Profit]]/Table2[[#This Row],[Cost]] -> 0.23331222 | BC10: August | BD10: =COUNTIF(Table2[[#All],[Month]],$BC10) -> 71 | BE10: =SUMIF(Table2[Month],BC10,Table2[Revenue]) -> 375497.65 | BF10: =SUMIF(Table2[[#All],[Month]],BC10,Table2[[#All],[SaleValue]]) -> 377733.91 | BG10: =SUMIF(Table2[[#All],[Month]],BC10,Table2[[#All],[Profit]]) -> 109707.94 | BH10: =(BE10-BE9)/BE9 -> -0.21513311
A11: 10 | B11: 2024-06-15 | C11: =YEAR(Table2[[#This Row],[Date]]) -> 2024 | D11: =TEXT(Table2[[#This Row],[Date]],"mmmm") -> June | E11: Riya | F11: South | G11: UK | H11: New York | I11: Office Supplies | J11: Jacket | K11: Retail | L11: Rep A | M11: 208.71 | N11: 9 | O11: 0.03 | P11: =IF(Table2[[#This Row],[Discount]]>20%,"HIGH","LOW") -> LOW | Q11: 1822.04 | R11: =_xlfn.IFS(Table2[[#This Row],[Revenue]]<1000,"Small",OR(Table2[[#This Row],[Revenue]]>1000,Table2[[#This Row],[Revenue]]<=5000),"Medium",Table2[[#This Row],[Revenue]]>5000,"Large") -> Medium | S11: =IF(Table2[[#This Row],[Revenue]]>3000,"Premium","Not Premium") -> Not Premium | T11: 1557.66 | U11: 264.38 | V11: UPI | W11: Medium | X11: Standard | Y11: 39.26 | Z11: 2 | AA11: =IF(Table2[[#This Row],[DeliveryDays]]<=3,"FAST DELIVERY","LATE DELIVERY") -> FAST DELIVERY | AB11: Home Office | AC11: No | AD11: 3 | AE11: =_xlfn.IFS(Table2[[#This Row],[Rating]]=5,"Excellent",Table2[[#This Row],[Rating]]=4,"Good",Table2[[#This Row],[Rating]]=3,"Average",Table2[[#This Row],[Rating]]<=2,"Poor") -> Average | AF11: =Table2[[#This Row],[Cost]]+Table2[[#This Row],[Profit]]+Table2[[#This Row],[ShippingCost]]+Table2[[#This Row],[DeliveryDays]] -> 1863.3 | AG11: =Table2[[#This Row],[Profit]]/Table2[[#This Row],[Cost]] -> 0.16972895 | AQ11: Find the maximum UnitPrice. | AY11: =MAX(WorkSheet_ANS!$M$1:$M$999) -> 999.66 | BC11: September | BD11: =COUNTIF(Table2[[#All],[Month]],$BC11) -> 86 | BE11: =SUMIF(Table2[Month],BC11,Table2[Revenue]) -> 398941.79 | BF11: =SUMIF(Table2[[#All],[Month]],BC11,Table2[[#All],[SaleValue]]) -> 401921.06 | BG11: =SUMIF(Table2[[#All],[Month]],BC11,Table2[[#All],[Profit]]) -> 126603.59 | BH11: =(BE11-BE10)/BE10 -> 0.062434851
A12: 11 | B12: 2023-02-07 | C12: =YEAR(Table2[[#This Row],[Date]]) -> 2023 | D12: =TEXT(Table2[[#This Row],[Date]],"mmmm") -> February | E12: Priya | F12: North | G12: Australia | H12: London | I12: Office Supplies | J12: Football | K12: Online | L12: Rep A | M12: 324.88 | N12: 16 | O12: 0.17 | P12: =IF(Table2[[#This Row],[Discount]]>20%,"HIGH","LOW") -> LOW | Q12: 4314.41 | R12: =_xlfn.IFS(Table2[[#This Row],[Revenue]]<1000,"Small",OR(Table2[[#This Row],[Revenue]]>1000,Table2[[#This Row],[Revenue]]<=5000),"Medium",Table2[[#This Row],[Revenue]]>5000,"Large") -> Medium | S12: =IF(Table2[[#This Row],[Revenue]]>3000,"Premium","Not Premium") -> Premium | T12: 3303.81 | U12: 1010.6 | V12: Bank Transfer | W12: Low | X12: Same Day | Y12: 33.2 | Z12: 4 | AA12: =IF(Table2[[#This Row],[DeliveryDays]]<=3,"FAST DELIVERY","LATE DELIVERY") -> LATE DELIVERY | AB12: Corporate | AC12: No | AD12: 4 | AE12: =_xlfn.IFS(Table2[[#This Row],[Rating]]=5,"Excellent",Table2[[#This Row],[Rating]]=4,"Good",Table2[[#This Row],[Rating]]=3,"Average",Table2[[#This Row],[Rating]]<=2,"Poor") -> Good | AF12: =Table2[[#This Row],[Cost]]+Table2[[#This Row],[Profit]]+Table2[[#This Row],[ShippingCost]]+Table2[[#This Row],[DeliveryDays]] -> 4351.61 | AG12: =Table2[[#This Row],[Profit]]/Table2[[#This Row],[Cost]] -> 0.30588926 | BC12: October | BD12: =COUNTIF(Table2[[#All],[Month]],$BC12) -> 84 | BE12: =SUMIF(Table2[Month],BC12,Table2[Revenue]) -> 397456.12 | BF12: =SUMIF(Table2[[#All],[Month]],BC12,Table2[[#All],[SaleValue]]) -> 400276.68 | BG12: =SUMIF(Table2[[#All],[Month]],BC12,Table2[[#All],[Profit]]) -> 125919.31 | BH12: =(BE12-BE11)/BE11 -> -0.003724027
A13: 12 | B13: 2024-07-22 | C13: =YEAR(Table2[[#This Row],[Date]]) -> 2024 | D13: =TEXT(Table2[[#This Row],[Date]],"mmmm") -> July | E13: Sara | F13: East | G13: Australia | H13: Sydney | I13: Sports | J13: Chair | K13: Online | L13: Rep D | M13: 89.82 | N13: 12 | O13: 0.16 | P13: =IF(Table2[[#This Row],[Discount]]>20%,"HIGH","LOW") -> LOW | Q13: 905.39 | R13: =_xlfn.IFS(Table2[[#This Row],[Revenue]]<1000,"Small",OR(Table2[[#This Row],[Revenue]]>1000,Table2[[#This Row],[Revenue]]<=5000),"Medium",Table2[[#This Row],[Revenue]]>5000,"Large") -> Small | S13: =IF(Table2[[#This Row],[Revenue]]>3000,"Premium","Not Premium") -> Not Premium | T13: 594.91 | U13: 310.48 | V13: Bank Transfer | W13: Medium | X13: Same Day | Y13: 13.9 | Z13: 8 | AA13: =IF(Table2[[#This Row],[DeliveryDays]]<=3,"FAST DELIVERY","LATE DELIVERY") -> LATE DELIVERY | AB13: Consumer | AC13: No | AD13: 4 | AE13: =_xlfn.IFS(Table2[[#This Row],[Rating]]=5,"Excellent",Table2[[#This Row],[Rating]]=4,"Good",Table2[[#This Row],[Rating]]=3,"Average",Table2[[#This Row],[Rating]]<=2,"Poor") -> Good | AF13: =Table2[[#This Row],[Cost]]+Table2[[#This Row],[Profit]]+Table2[[#This Row],[ShippingCost]]+Table2[[#This Row],[DeliveryDays]] -> 927.29 | AG13: =Table2[[#This Row],[Profit]]/Table2[[#This Row],[Cost]] -> 0.52189407 | AQ13: Find the minimum UnitPrice. | AY13: =MIN(WorkSheet_ANS!$M$1:$M$999) -> 12.57 | BC13: November | BD13: =COUNTIF(Table2[[#All],[Month]],$BC13) -> 71 | BE13: =SUMIF(Table2[Month],BC13,Table2[Revenue]) -> 298662.64 | BF13: =SUMIF(Table2[[#All],[Month]],BC13,Table2[[#All],[SaleValue]]) -> 300850.43 | BG13: =SUMIF(Table2[[#All],[Month]],BC13,Table2[[#All],[Profit]]) -> 85355.5 | BH13: =(BE13-BE12)/BE12 -> -0.2485645
A14: 13 | B14: 2023-06-12 | C14: =YEAR(Table2[[#This Row],[Date]]) -> 2023 | D14: =TEXT(Table2[[#This Row],[Date]],"mmmm") -> June | E14: Anita | F14: West | G14: Germany | H14: Toronto | I14: Clothing | J14: Jacket | K14: Distributor | L14: Rep B | M14: 387.73 | N14: 6 | O14: 0.19 | P14: =IF(Table2[[#This Row],[Discount]]>20%,"HIGH","LOW") -> LOW | Q14: 1884.37 | R14: =_xlfn.IFS(Table2[[#This Row],[Revenue]]<1000,"Small",OR(Table2[[#This Row],[Revenue]]>1000,Table2[[#This Row],[Revenue]]<=5000),"Medium",Table2[[#This Row],[Revenue]]>5000,"Large") -> Medium | S14: =IF(Table2[[#This Row],[Revenue]]>3000,"Premium","Not Premium") -> Not Premium | T14: 1273.7 | U14: 610.67 | V14: PayPal | W14: Medium | X14: Standard | Y14: 20.17 | Z14: 1 | AA14: =IF(Table2[[#This Row],[DeliveryDays]]<=3,"FAST DELIVERY","LATE DELIVERY") -> FAST DELIVERY | AB14: Consumer | AC14: Yes | AD14: 2 | AE14: =_xlfn.IFS(Table2[[#This Row],[Rating]]=5,"Excellent",Table2[[#This Row],[Rating]]=4,"Good",Table2[[#This Row],[Rating]]=3,"Average",Table2[[#This Row],[Rating]]<=2,"Poor") -> Poor | AF14: =Table2[[#This Row],[Cost]]+Table2[[#This Row],[Profit]]+Table2[[#This Row],[ShippingCost]]+Table2[[#This Row],[DeliveryDays]] -> 1905.54 | AG14: =Table2[[#This Row],[Profit]]/Table2[[#This Row],[Cost]] -> 0.47944571 | BC14: December | BD14: =COUNTIF(Table2[[#All],[Month]],$BC14) -> 100 | BE14: =SUMIF(Table2[Month],BC14,Table2[Revenue]) -> 444211.16 | BF14: =SUMIF(Table2[[#All],[Month]],BC14,Table2[[#All],[SaleValue]]) -> 447548.01 | BG14: =SUMIF(Table2[[#All],[Month]],BC14,Table2[[#All],[Profit]]) -> 129365.17 | BH14: =(BE14-BE13)/BE13 -> 0.4873342
A15: 14 | B15: 2023-03-30 | C15: =YEAR(Table2[[#This Row],[Date]]) -> 2023 | D15: =TEXT(Table2[[#This Row],[Date]],"mmmm") -> March | E15: Anita | F15: North | G15: Germany | H15: Toronto | I15: Clothing | J15: Laptop | K15: Retail | L15: Rep E | M15: 49.49 | N15: 12 | O15: 0.18 | P15: =IF(Table2[[#This Row],[Discount]]>20%,"HIGH","LOW") -> LOW | Q15: 486.98 | R15: =_xlfn.IFS(Table2[[#This Row],[Revenue]]<1000,"Small",OR(Table2[[#This Row],[Revenue]]>1000,Table2[[#This Row],[Revenue]]<=5000),"Medium",Table2[[#This Row],[Revenue]]>5000,"Large") -> Small | S15: =IF(Table2[[#This Row],[Revenue]]>3000,"Premium","Not Premium") -> Not Premium | T15: 396.26 | U15: 90.72 | V15: Cash | W15: Low | X15: Standard | Y15: 28.4 | Z15: 5 | AA15: =IF(Table2[[#This Row],[DeliveryDays]]<=3,"FAST DELIVERY","LATE DELIVERY") -> LATE DELIVERY | AB15: Home Office | AC15: Yes | AD15: 3 | AE15: =_xlfn.IFS(Table2[[#This Row],[Rating]]=5,"Excellent",Table2[[#This Row],[Rating]]=4,"Good",Table2[[#This Row],[Rating]]=3,"Average",Table2[[#This Row],[Rating]]<=2,"Poor") -> Average | AF15: =Table2[[#This Row],[Cost]]+Table2[[#This Row],[Profit]]+Table2[[#This Row],[ShippingCost]]+Table2[[#This Row],[DeliveryDays]] -> 520.38 | AG15: =Table2[[#This Row],[Profit]]/Table2[[#This Row],[Cost]] -> 0.22894059 | AQ15: Find average Quantity sold per order. | AY15: =AVERAGE(WorkSheet_ANS!$N$2:$N$999) -> 10.498998
A16: 15 | B16: 2023-06-14 | C16: =YEAR(Table2[[#This Row],[Date]]) -> 2023 | D16: =TEXT(Table2[[#This Row],[Date]],"mmmm") -> June | E16: Priya | F16: South | G16: Canada | H16: London | I16: Electronics | J16: T-Shirt | K16: Distributor | L16: Rep E | M16: 66.03 | N16: 4 | O16: 0.03 | P16: =IF(Table2[[#This Row],[Discount]]>20%,"HIGH","LOW") -> LOW | Q16: 256.2 | R16: =_xlfn.IFS(Table2[[#This Row],[Revenue]]<1000,"Small",OR(Table2[[#This Row],[Revenue]]>1000,Table2[[#This Row],[Revenue]]<=5000),"Medium",Table2[[#This Row],[Revenue]]>5000,"Large") -> Small | S16: =IF(Table2[[#This Row],[Revenue]]>3000,"Premium","Not Premium") -> Not Premium | T16: 228.6 | U16: 27.6 | V16: Bank Transfer | W16: Low | X16: Same Day | Y16: 18.99 | Z16: 4 | AA16: =IF(Table2[[#This Row],[DeliveryDays]]<=3,"FAST DELIVERY","LATE DELIVERY") -> LATE DELIVERY | AB16: Consumer | AC16: Yes | AD16: 3 | AE16: =_xlfn.IFS(Table2[[#This Row],[Rating]]=5,"Excellent",Table2[[#This Row],[Rating]]=4,"Good",Table2[[#This Row],[Rating]]=3,"Average",Table2[[#This Row],[Rating]]<=2,"Poor") -> Average | AF16: =Table2[[#This Row],[Cost]]+Table2[[#This Row],[Profit]]+Table2[[#This Row],[ShippingCost]]+Table2[[#This Row],[DeliveryDays]] -> 279.19 | AG16: =Table2[[#This Row],[Profit]]/Table2[[#This Row],[Cost]] -> 0.12073491 | BC16: Find Month with highest revenue.
A17: 16 | B17: 2024-12-25 | C17: =YEAR(Table2[[#This Row],[Date]]) -> 2024 | D17: =TEXT(Table2[[#This Row],[Date]],"mmmm") -> December | E17: Michael | F17: North | G17: Canada | H17: Berlin | I17: Clothing | J17: Football | K17: Retail | L17: Rep E | M17: 687.05 | N17: 19 | O17: 0.18 | P17: =IF(Table2[[#This Row],[Discount]]>20%,"HIGH","LOW") -> LOW | Q17: 10704.24 | R17: =_xlfn.IFS(Table2[[#This Row],[Revenue]]<1000,"Small",OR(Table2[[#This Row],[Revenue]]>1000,Table2[[#This Row],[Revenue]]<=5000),"Medium",Table2[[#This Row],[Revenue]]>5000,"Large") -> Medium | S17: =IF(Table2[[#This Row],[Revenue]]>3000,"Premium","Not Premium") -> Premium | T17: 7654.15 | U17: 3050.09 | V17: Credit Card | W17: High | X17: Express | Y17: 25.82 | Z17: 3 | AA17: =IF(Table2[[#This Row],[DeliveryDays]]<=3,"FAST DELIVERY","LATE DELIVERY") -> FAST DELIVERY | AB17: Corporate | AC17: Yes | AD17: 3 | AE17: =_xlfn.IFS(Table2[[#This Row],[Rating]]=5,"Excellent",Table2[[#This Row],[Rating]]=4,"Good",Table2[[#This Row],[Rating]]=3,"Average",Table2[[#This Row],[Rating]]<=2,"Poor") -> Average | AF17: =Table2[[#This Row],[Cost]]+Table2[[#This Row],[Profit]]+Table2[[#This Row],[ShippingCost]]+Table2[[#This Row],[DeliveryDays]] -> 10733.06 | AG17: =Table2[[#This Row],[Profit]]/Table2[[#This Row],[Cost]] -> 0.3984884 | AQ17: Find maximum Quantity sold. | AY17: =MAX(WorkSheet_ANS!$N$2:$N$999) -> 20
A18: 17 | B18: 2023-08-05 | C18: =YEAR(Table2[[#This Row],[Date]]) -> 2023 | D18: =TEXT(Table2[[#This Row],[Date]],"mmmm") -> August | E18: Priya | F18: North | G18: Canada | H18: Pune | I18: Clothing | J18: Football | K18: Distributor | L18: Rep E | M18: 725.8 | N18: 8 | O18: 0.15 | P18: =IF(Table2[[#This Row],[Discount]]>20%,"HIGH","LOW") -> LOW | Q18: 4935.44 | R18: =_xlfn.IFS(Table2[[#This Row],[Revenue]]<1000,"Small",OR(Table2[[#This Row],[Revenue]]>1000,Table2[[#This Row],[Revenue]]<=5000),"Medium",Table2[[#This Row],[Revenue]]>5000,"Large") -> Medium | S18: =IF(Table2[[#This Row],[Revenue]]>3000,"Premium","Not Premium") -> Premium | T18: 3662.25 | U18: 1273.19 | V18: Bank Transfer | W18: Critical | X18: Same Day | Y18: 29.54 | Z18: 6 | AA18: =IF(Table2[[#This Row],[DeliveryDays]]<=3,"FAST DELIVERY","LATE DELIVERY") -> LATE DELIVERY | AB18: Corporate | AC18: Yes | AD18: 1 | AE18: =_xlfn.IFS(Table2[[#This Row],[Rating]]=5,"Excellent",Table2[[#This Row],[Rating]]=4,"Good",Table2[[#This Row],[Rating]]=3,"Average",Table2[[#This Row],[Rating]]<=2,"Poor") -> Poor | AF18: =Table2[[#This Row],[Cost]]+Table2[[#This Row],[Profit]]+Table2[[#This Row],[ShippingCost]]+Table2[[#This Row],[DeliveryDays]] -> 4970.98 | AG18: =Table2[[#This Row],[Profit]]/Table2[[#This Row],[Cost]] -> 0.3476524 | BC18: Highest revenue | BD18: Month
A19: 18 | B19: 2024-11-09 | C19: =YEAR(Table2[[#This Row],[Date]]) -> 2024 | D19: =TEXT(Table2[[#This Row],[Date]],"mmmm") -> November | E19: Sophia | F19: South | G19: UK | H19: London | I19: Sports | J19: Printer | K19: Retail | L19: Rep D | M19: 370.13 | N19: 1 | O19: 0.12 | P19: =IF(Table2[[#This Row],[Discount]]>20%,"HIGH","LOW") -> LOW | Q19: 325.71 | R19: =_xlfn.IFS(Table2[[#This Row],[Revenue]]<1000,"Small",OR(Table2[[#This Row],[Revenue]]>1000,Table2[[#This Row],[Revenue]]<=5000),"Medium",Table2[[#This Row],[Revenue]]>5000,"Large") -> Small | S19: =IF(Table2[[#This Row],[Revenue]]>3000,"Premium","Not Premium") -> Not Premium | T19: 263 | U19: 62.71 | V19: Cash | W19: Critical | X19: Standard | Y19: 40.28 | Z19: 9 | AA19: =IF(Table2[[#This Row],[DeliveryDays]]<=3,"FAST DELIVERY","LATE DELIVERY") -> LATE DELIVERY | AB19: Corporate | AC19: No | AD19: 4 | AE19: =_xlfn.IFS(Table2[[#This Row],[Rating]]=5,"Excellent",Table2[[#This Row],[Rating]]=4,"Good",Table2[[#This Row],[Rating]]=3,"Average",Table2[[#This Row],[Rating]]<=2,"Poor") -> Good | AF19: =Table2[[#This Row],[Cost]]+Table2[[#This Row],[Profit]]+Table2[[#This Row],[ShippingCost]]+Table2[[#This Row],[DeliveryDays]] -> 374.99 | AG19: =Table2[[#This Row],[Profit]]/Table2[[#This Row],[Cost]] -> 0.23844106 | AQ19: Find minimum Quantity sold. | AY19: =MIN(WorkSheet_ANS!$N$2:$N$999) -> 1 | BC19: =MAX(Table2[[#All],[Revenue]]) -> 18384.66 | BD19: =INDEX(Table2[[#All],[Month]],MATCH($BC$19,Table2[[#All],[Revenue]],0),0) -> February
A20: 19 | B20: 2024-12-27 | C20: =YEAR(Table2[[#This Row],[Date]]) -> 2024 | D20: =TEXT(Table2[[#This Row],[Date]],"mmmm") -> December | E20: Sara | F20: East | G20: USA | H20: Mumbai | I20: Electronics | J20: Printer | K20: Distributor | L20: Rep C | M20: 592.47 | N20: 19 | O20: 0.08 | P20: =IF(Table2[[#This Row],[Discount]]>20%,"HIGH","LOW") -> LOW | Q20: 10356.38 | R20: =_xlfn.IFS(Table2[[#This Row],[Revenue]]<1000,"Small",OR(Table2[[#This Row],[Revenue]]>1000,Table2[[#This Row],[Revenue]]<=5000),"Medium",Table2[[#This Row],[Revenue]]>5000,"Large") -> Medium | S20: =IF(Table2[[#This Row],[Revenue]]>3000,"Premium","Not Premium") -> Premium | T20: 8696.16 | U20: 1660.22 | V20: PayPal | W20: Critical | X20: Standard | Y20: 16.1 | Z20: 3 | AA20: =IF(Table2[[#This Row],[DeliveryDays]]<=3,"FAST DELIVERY","LATE DELIVERY") -> FAST DELIVERY | AB20: Consumer | AC20: Yes | AD20: 5 | AE20: =_xlfn.IFS(Table2[[#This Row],[Rating]]=5,"Excellent",Table2[[#This Row],[Rating]]=4,"Good",Table2[[#This Row],[Rating]]=3,"Average",Table2[[#This Row],[Rating]]<=2,"Poor") -> Excellent | AF20: =Table2[[#This Row],[Cost]]+Table2[[#This Row],[Profit]]+Table2[[#This Row],[ShippingCost]]+Table2[[#This Row],[DeliveryDays]] -> 10375.48 | AG20: =Table2[[#This Row],[Profit]]/Table2[[#This Row],[Cost]] -> 0.19091415
A21: 20 | B21: 2023-12-07 | C21: =YEAR(Table2[[#This Row],[Date]]) -> 2023 | D21: =TEXT(Table2[[#This Row],[Date]],"mmmm") -> December | E21: Riya | F21: East | G21: UK | H21: Sydney | I21: Sports | J21: Jacket | K21: Retail | L21: Rep C | M21: 548.16 | N21: 1 | O21: 0.21 | P21: =IF(Table2[[#This Row],[Discount]]>20%,"HIGH","LOW") -> HIGH | Q21: 433.05 | R21: =_xlfn.IFS(Table2[[#This Row],[Revenue]]<1000,"Small",OR(Table2[[#This Row],[Revenue]]>1000,Table2[[#This Row],[Revenue]]<=5000),"Medium",Table2[[#This Row],[Revenue]]>5000,"Large") -> Small | S21: =IF(Table2[[#This Row],[Revenue]]>3000,"Premium","Not Premium") -> Not Premium | T21: 297.44 | U21: 135.61 | V21: Credit Card | W21: Medium | X21: Same Day | Y21: 33.45 | Z21: 7 | AA21: =IF(Table2[[#This Row],[DeliveryDays]]<=3,"FAST DELIVERY","LATE DELIVERY") -> LATE DELIVERY | AB21: Corporate | AC21: Yes | AD21: 3 | AE21: =_xlfn.IFS(Table2[[#This Row],[Rating]]=5,"Excellent",Table2[[#This Row],[Rating]]=4,"Good",Table2[[#This Row],[Rating]]=3,"Average",Table2[[#This Row],[Rating]]<=2,"Poor") -> Average | AF21: =Table2[[#This Row],[Cost]]+Table2[[#This Row],[Profit]]+Table2[[#This Row],[ShippingCost]]+Table2[[#This Row],[DeliveryDays]] -> 473.5 | AG21: =Table2[[#This Row],[Profit]]/Table2[[#This Row],[Cost]] -> 0.45592388 | AQ21: Calculate Total Revenue. | AY21: =SUM(WorkSheet_ANS!$Q$2:$Q$999) -> 4400793.2 | BC21: Find best performing month. | BF21: =INDEX(BC2:BC14,MATCH(MAX(BE2:BE14),BE2:BE14,0),0) -> July
A22: 21 | B22: 2024-08-23 | C22: =YEAR(Table2[[#This Row],[Date]]) -> 2024 | D22: =TEXT(Table2[[#This Row],[Date]],"mmmm") -> August | E22: Riya | F22: West | G22: USA | H22: Sydney | I22: Clothing | J22: Keyboard | K22: Retail | L22: Rep B | M22: 839.45 | N22: 6 | O22: 0.3 | P22: =IF(Table2[[#This Row],[Discount]]>20%,"HIGH","LOW") -> HIGH | Q22: 3525.69 | R22: =_xlfn.IFS(Table2[[#This Row],[Revenue]]<1000,"Small",OR(Table2[[#This Row],[Revenue]]>1000,Table2[[#This Row],[Revenue]]<=5000),"Medium",Table2[[#This Row],[Revenue]]>5000,"Large") -> Medium | S22: =IF(Table2[[#This Row],[Revenue]]>3000,"Premium","Not Premium") -> Premium | T22: 2289.81 | U22: 1235.88 | V22: Cash | W22: High | X22: Same Day | Y22: 49.92 | Z22: 1 | AA22: =IF(Table2[[#This Row],[DeliveryDays]]<=3,"FAST DELIVERY","LATE DELIVERY") -> FAST DELIVERY | AB22: Corporate | AC22: No | AD22: 3 | AE22: =_xlfn.IFS(Table2[[#This Row],[Rating]]=5,"Excellent",Table2[[#This Row],[Rating]]=4,"Good",Table2[[#This Row],[Rating]]=3,"Average",Table2[[#This Row],[Rating]]<=2,"Poor") -> Average | AF22: =Table2[[#This Row],[Cost]]+Table2[[#This Row],[Profit]]+Table2[[#This Row],[ShippingCost]]+Table2[[#This Row],[DeliveryDays]] -> 3576.61 | AG22: =Table2[[#This Row],[Profit]]/Table2[[#This Row],[Cost]] -> 0.53973037
A23: 22 | B23: 2024-11-14 | C23: =YEAR(Table2[[#This Row],[Date]]) -> 2024 | D23: =TEXT(Table2[[#This Row],[Date]],"mmmm") -> November | E23: Sara | F23: South | G23: Canada | H23: Mumbai | I23: Electronics | J23: Football | K23: Online | L23: Rep C | M23: 433.56 | N23: 16 | O23: 0.08 | P23: =IF(Table2[[#This Row],[Discount]]>20%,"HIGH","LOW") -> LOW | Q23: 6382 | R23: =_xlfn.IFS(Table2[[#This Row],[Revenue]]<1000,"Small",OR(Table2[[#This Row],[Revenue]]>1000,Table2[[#This Row],[Revenue]]<=5000),"Medium",Table2[[#This Row],[Revenue]]>5000,"Large") -> Medium | S23: =IF(Table2[[#This Row],[Revenue]]>3000,"Premium","Not Premium") -> Premium | T23: 4078.68 | U23: 2303.32 | V23: Cash | W23: Medium | X23: Same Day | Y23: 5.44 | Z23: 8 | AA23: =IF(Table2[[#This Row],[DeliveryDays]]<=3,"FAST DELIVERY","LATE DELIVERY") -> LATE DELIVERY | AB23: Consumer | AC23: No | AD23: 2 | AE23: =_xlfn.IFS(Table2[[#This Row],[Rating]]=5,"Excellent",Table2[[#This Row],[Rating]]=4,"Good",Table2[[#This Row],[Rating]]=3,"Average",Table2[[#This Row],[Rating]]<=2,"Poor") -> Poor | AF23: =Table2[[#This Row],[Cost]]+Table2[[#This Row],[Profit]]+Table2[[#This Row],[ShippingCost]]+Table2[[#This Row],[DeliveryDays]] -> 6395.44 | AG23: =Table2[[#This Row],[Profit]]/Table2[[#This Row],[Cost]] -> 0.56472192 | AQ23: Calculate Total Cost. | AY23: =SUM(WorkSheet_ANS!$T$2:$T$999) -> 3069234.7 | BC23: Find worst performing month. | BF23: =INDEX(BC2:BC14,MATCH(MIN(BE2:BE14),BE2:BE14,0),0) -> April
A24: 23 | B24: 2023-01-15 | C24: =YEAR(Table2[[#This Row],[Date]]) -> 2023 | D24: =TEXT(Table2[[#This Row],[Date]],"mmmm") -> January | E24: Riya | F24: East | G24: Canada | H24: Sydney | I24: Sports | J24: Jacket | K24: Retail | L24: Rep A | M24: 769.36 | N24: 18 | O24: 0.15 | P24: =IF(Table2[[#This Row],[Discount]]>20%,"HIGH","LOW") -> LOW | Q24: 11771.21 | R24: =_xlfn.IFS(Table2[[#This Row],[Revenue]]<1000,"Small",OR(Table2[[#This Row],[Revenue]]>1000,Table2[[#This Row],[Revenue]]<=5000),"Medium",Table2[[#This Row],[Revenue]]>5000,"Large") -> Medium | S24: =IF(Table2[[#This Row],[Revenue]]>3000,"Premium","Not Premium") -> Premium | T24: 8865.18 | U24: 2906.03 | V24: PayPal | W24: Critical | X24: Same Day | Y24: 44.03 | Z24: 3 | AA24: =IF(Table2[[#This Row],[DeliveryDays]]<=3,"FAST DELIVERY","LATE DELIVERY") -> FAST DELIVERY | AB24: Consumer | AC24: Yes | AD24: 3 | AE24: =_xlfn.IFS(Table2[[#This Row],[Rating]]=5,"Excellent",Table2[[#This Row],[Rating]]=4,"Good",Table2[[#This Row],[Rating]]=3,"Average",Table2[[#This Row],[Rating]]<=2,"Poor") -> Average | AF24: =Table2[[#This Row],[Cost]]+Table2[[#This Row],[Profit]]+Table2[[#This Row],[ShippingCost]]+Table2[[#This Row],[DeliveryDays]] -> 11818.24 | AG24: =Table2[[#This Row],[Profit]]/Table2[[#This Row],[Cost]] -> 0.32780271
A25: 24 | B25: 2023-03-11 | C25: =YEAR(Table2[[#This Row],[Date]]) -> 2023 | D25: =TEXT(Table2[[#This Row],[Date]],"mmmm") -> March | E25: Rahul | F25: West | G25: Canada | H25: Berlin | I25: Furniture | J25: Chair | K25: Retail | L25: Rep A | M25: 735.29 | N25: 14 | P25: =IF(Table2[[#This Row],[Discount]]>20%,"HIGH","LOW") -> LOW | Q25: 7205.84 | R25: =_xlfn.IFS(Table2[[#This Row],[Revenue]]<1000,"Small",OR(Table2[[#This Row],[Revenue]]>1000,Table2[[#This Row],[Revenue]]<=5000),"Medium",Table2[[#This Row],[Revenue]]>5000,"Large") -> Medium | S25: =IF(Table2[[#This Row],[Revenue]]>3000,"Premium","Not Premium") -> Premium | T25: 6440.47 | U25: 765.37 | V25: PayPal | W25: High | X25: Same Day | Y25: 22.18 | Z25: 4 | AA25: =IF(Table2[[#This Row],[DeliveryDays]]<=3,"FAST DELIVERY","LATE DELIVERY") -> LATE DELIVERY | AB25: Corporate | AC25: Yes | AD25: 1 | AE25: =_xlfn.IFS(Table2[[#This Row],[Rating]]=5,"Excellent",Table2[[#This Row],[Rating]]=4,"Good",Table2[[#This Row],[Rating]]=3,"Average",Table2[[#This Row],[Rating]]<=2,"Poor") -> Poor | AF25: =Table2[[#This Row],[Cost]]+Table2[[#This Row],[Profit]]+Table2[[#This Row],[ShippingCost]]+Table2[[#This Row],[DeliveryDays]] -> 7232.02 | AG25: =Table2[[#This Row],[Profit]]/Table2[[#This Row],[Cost]] -> 0.1188376 | AQ25: Calculate Total Profit. | AY25: =SUM(WorkSheet_ANS!$U$2:$U$999) -> 1331558.5 | BC25: Identify lowest profit margin product. | BI25: =MIN(Table2[Profit Margin]) -> 0.11236077
A26: 25 | B26: 2024-08-24 | C26: =YEAR(Table2[[#This Row],[Date]]) -> 2024 | D26: =TEXT(Table2[[#This Row],[Date]],"mmmm") -> August | E26: Priya | F26: South | G26: Germany | H26: Delhi | I26: Electronics | J26: T-Shirt | K26: Retail | L26: Rep B | M26: 823.06 | N26: 6 | O26: 0.1 | P26: =IF(Table2[[#This Row],[Discount]]>20%,"HIGH","LOW") -> LOW | Q26: 4444.52 | R26: =_xlfn.IFS(Table2[[#This Row],[Revenue]]<1000,"Small",OR(Table2[[#This Row],[Revenue]]>1000,Table2[[#This Row],[Revenue]]<=5000),"Medium",Table2[[#This Row],[Revenue]]>5000,"Large") -> Medium | S26: =IF(Table2[[#This Row],[Revenue]]>3000,"Premium","Not Premium") -> Premium | T26: 3447.91 | U26: 996.61 | V26: PayPal | W26: Medium | X26: Express | Y26: 10.2 | Z26: 1 | AA26: =IF(Table2[[#This Row],[DeliveryDays]]<=3,"FAST DELIVERY","LATE DELIVERY") -> FAST DELIVERY | AB26: Consumer | AC26: Yes | AD26: 5 | AE26: =_xlfn.IFS(Table2[[#This Row],[Rating]]=5,"Excellent",Table2[[#This Row],[Rating]]=4,"Good",Table2[[#This Row],[Rating]]=3,"Average",Table2[[#This Row],[Rating]]<=2,"Poor") -> Excellent | AF26: =Table2[[#This Row],[Cost]]+Table2[[#This Row],[Profit]]+Table2[[#This Row],[ShippingCost]]+Table2[[#This Row],[DeliveryDays]] -> 4455.72 | AG26: =Table2[[#This Row],[Profit]]/Table2[[#This Row],[Cost]] -> 0.28904757
A27: 26 | B27: 2024-07-01 | C27: =YEAR(Table2[[#This Row],[Date]]) -> 2024 | D27: =TEXT(Table2[[#This Row],[Date]],"mmmm") -> July | E27: Sophia | F27: North | G27: UK | H27: Mumbai | I27: Clothing | J27: Laptop | K27: Online | L27: Rep E | M27: 710.55 | N27: 10 | O27: 0.09 | P27: =IF(Table2[[#This Row],[Discount]]>20%,"HIGH","LOW") -> LOW | Q27: 6466.01 | R27: =_xlfn.IFS(Table2[[#This Row],[Revenue]]<1000,"Small",OR(Table2[[#This Row],[Revenue]]>1000,Table2[[#This Row],[Revenue]]<=5000),"Medium",Table2[[#This Row],[Revenue]]>5000,"Large") -> Medium | S27: =IF(Table2[[#This Row],[Revenue]]>3000,"Premium","Not Premium") -> Premium | T27: 5293.17 | U27: 1172.84 | V27: Credit Card | W27: Medium | X27: Standard | Y27: 10.52 | Z27: 7 | AA27: =IF(Table2[[#This Row],[DeliveryDays]]<=3,"FAST DELIVERY","LATE DELIVERY") -> LATE DELIVERY | AB27: Consumer | AC27: Yes | AD27: 2 | AE27: =_xlfn.IFS(Table2[[#This Row],[Rating]]=5,"Excellent",Table2[[#This Row],[Rating]]=4,"Good",Table2[[#This Row],[Rating]]=3,"Average",Table2[[#This Row],[Rating]]<=2,"Poor") -> Poor | AF27: =Table2[[#This Row],[Cost]]+Table2[[#This Row],[Profit]]+Table2[[#This Row],[ShippingCost]]+Table2[[#This Row],[DeliveryDays]] -> 6483.53 | AG27: =Table2[[#This Row],[Profit]]/Table2[[#This Row],[Cost]] -> 0.22157611 | AQ27: Calculate Average Profit per Order. | AY27: =AVERAGE(WorkSheet_ANS!$U$2:$U$999) -> 1334.227 | BC27: Identify highest profit margin product. | BI27: =MAX(Table2[Profit Margin]) -> 0.99627411
A28: 27 | B28: 2023-04-27 | C28: =YEAR(Table2[[#This Row],[Date]]) -> 2023 | D28: =TEXT(Table2[[#This Row],[Date]],"mmmm") -> April | E28: Arjun | F28: North | G28: India | H28: New York | I28: Electronics | J28: Football | K28: Online | L28: Rep E | M28: 600.43 | N28: 17 | O28: 0.17 | P28: =IF(Table2[[#This Row],[Discount]]>20%,"HIGH","LOW") -> LOW | Q28: 8472.07 | R28: =_xlfn.IFS(Table2[[#This Row],[Revenue]]<1000,"Small",OR(Table2[[#This Row],[Revenue]]>1000,Table2[[#This Row],[Revenue]]<=5000),"Medium",Table2[[#This Row],[Revenue]]>5000,"Large") -> Medium | S28: =IF(Table2[[#This Row],[Revenue]]>3000,"Premium","Not Premium") -> Premium | T28: 4854.92 | U28: 3617.15 | V28: Credit Card | W28: Low | X28: Same Day | Y28: 12.96 | Z28: 6 | AA28: =IF(Table2[[#This Row],[DeliveryDays]]<=3,"FAST DELIVERY","LATE DELIVERY") -> LATE DELIVERY | AB28: Home Office | AC28: Yes | AD28: 5 | AE28: =_xlfn.IFS(Table2[[#This Row],[Rating]]=5,"Excellent",Table2[[#This Row],[Rating]]=4,"Good",Table2[[#This Row],[Rating]]=3,"Average",Table2[[#This Row],[Rating]]<=2,"Poor") -> Excellent | AF28: =Table2[[#This Row],[Cost]]+Table2[[#This Row],[Profit]]+Table2[[#This Row],[ShippingCost]]+Table2[[#This Row],[DeliveryDays]] -> 8491.03 | AG28: =Table2[[#This Row],[Profit]]/Table2[[#This Row],[Cost]] -> 0.74504832
A29: 28 | B29: 2023-05-19 | C29: =YEAR(Table2[[#This Row],[Date]]) -> 2023 | D29: =TEXT(Table2[[#This Row],[Date]],"mmmm") -> May | E29: Amit | F29: North | G29: India | H29: Toronto | I29: Electronics | J29: T-Shirt | K29: Retail | L29: Rep D | M29: 697.99 | N29: 7 | O29: 0.1 | P29: =IF(Table2[[#This Row],[Discount]]>20%,"HIGH","LOW") -> LOW | Q29: 4397.34 | R29: =_xlfn.IFS(Table2[[#This Row],[Revenue]]<1000,"Small",OR(Table2[[#This Row],[Revenue]]>1000,Table2[[#This Row],[Revenue]]<=5000),"Medium",Table2[[#This Row],[Revenue]]>5000,"Large") -> Medium | S29: =IF(Table2[[#This Row],[Revenue]]>3000,"Premium","Not Premium") -> Premium | T29: 2823.58 | U29: 1573.76 | V29: UPI | W29: Critical | X29: Same Day | Y29: 27.37 | Z29: 1 | AA29: =IF(Table2[[#This Row],[DeliveryDays]]<=3,"FAST DELIVERY","LATE DELIVERY") -> FAST DELIVERY | AB29: Consumer | AC29: Yes | AD29: 5 | AE29: =_xlfn.IFS(Table2[[#This Row],[Rating]]=5,"Excellent",Table2[[#This Row],[Rating]]=4,"Good",Table2[[#This Row],[Rating]]=3,"Average",Table2[[#This Row],[Rating]]<=2,"Poor") -> Excellent | AF29: =Table2[[#This Row],[Cost]]+Table2[[#This Row],[Profit]]+Table2[[#This Row],[ShippingCost]]+Table2[[#This Row],[DeliveryDays]] -> 4425.71 | AG29: =Table2[[#This Row],[Profit]]/Table2[[#This Row],[Cost]] -> 0.55736335 | AQ29: Calculate Average Revenue per Order. | AY29: =AVERAGE(WorkSheet_ANS!$Q$2:$Q$999) -> 4409.6124
A30: 29 | B30: 2024-07-30 | C30: =YEAR(Table2[[#This Row],[Date]]) -> 2024 | D30: =TEXT(Table2[[#This Row],[Date]],"mmmm") -> July | E30: Arjun | F30: East | G30: UK | H30: Sydney | I30: Electronics | J30: Laptop | K30: Online | L30: Rep E | M30: 701.56 | N30: 3 | O30: 0.14 | P30: =IF(Table2[[#This Row],[Discount]]>20%,"HIGH","LOW") -> LOW | Q30: 1810.02 | R30: =_xlfn.IFS(Table2[[#This Row],[Revenue]]<1000,"Small",OR(Table2[[#This Row],[Revenue]]>1000,Table2[[#This Row],[Revenue]]<=5000),"Medium",Table2[[#This Row],[Revenue]]>5000,"Large") -> Medium | S30: =IF(Table2[[#This Row],[Revenue]]>3000,"Premium","Not Premium") -> Not Premium | T30: 1148.8 | U30: 661.22 | V30: PayPal | W30: High | X30: Standard | Y30: 37.53 | Z30: 7 | AA30: =IF(Table2[[#This Row],[DeliveryDays]]<=3,"FAST DELIVERY","LATE DELIVERY") -> LATE DELIVERY | AB30: Corporate | AC30: No | AD30: 3 | AE30: =_xlfn.IFS(Table2[[#This Row],[Rating]]=5,"Excellent",Table2[[#This Row],[Rating]]=4,"Good",Table2[[#This Row],[Rating]]=3,"Average",Table2[[#This Row],[Rating]]<=2,"Poor") -> Average | AF30: =Table2[[#This Row],[Cost]]+Table2[[#This Row],[Profit]]+Table2[[#This Row],[ShippingCost]]+Table2[[#This Row],[DeliveryDays]] -> 1854.55 | AG30: =Table2[[#This Row],[Profit]]/Table2[[#This Row],[Cost]] -> 0.57557451
A31: 30 | B31: 2023-04-09 | C31: =YEAR(Table2[[#This Row],[Date]]) -> 2023 | D31: =TEXT(Table2[[#This Row],[Date]],"mmmm") -> April | E31: Anita | F31: East | G31: India | H31: Mumbai | I31: Furniture | J31: T-Shirt | K31: Online | L31: Rep E | M31: 471.7 | N31: 14 | O31: 0.27 | P31: =IF(Table2[[#This Row],[Discount]]>20%,"HIGH","LOW") -> HIGH | Q31: 4820.77 | R31: =_xlfn.IFS(Table2[[#This Row],[Revenue]]<1000,"Small",OR(Table2[[#This Row],[Revenue]]>1000,Table2[[#This Row],[Revenue]]<=5000),"Medium",Table2[[#This Row],[Revenue]]>5000,"Large") -> Medium | S31: =IF(Table2[[#This Row],[Revenue]]>3000,"Premium","Not Premium") -> Premium | T31: 3546.14 | U31: 1274.63 | V31: Bank Transfer | W31: Medium | X31: Express | Y31: 29.81 | Z31: 2 | AA31: =IF(Table2[[#This Row],[DeliveryDays]]<=3,"FAST DELIVERY","LATE DELIVERY") -> FAST DELIVERY | AB31: Consumer | AC31: No | AD31: 5 | AE31: =_xlfn.IFS(Table2[[#This Row],[Rating]]=5,"Excellent",Table2[[#This Row],[Rating]]=4,"Good",Table2[[#This Row],[Rating]]=3,"Average",Table2[[#This Row],[Rating]]<=2,"Poor") -> Excellent | AF31: =Table2[[#This Row],[Cost]]+Table2[[#This Row],[Profit]]+Table2[[#This Row],[ShippingCost]]+Table2[[#This Row],[DeliveryDays]] -> 4852.58 | AG31: =Table2[[#This Row],[Profit]]/Table2[[#This Row],[Cost]] -> 0.35944153 | AQ31: Show only Electronics products.
A32: 31 | B32: 2023-09-10 | C32: =YEAR(Table2[[#This Row],[Date]]) -> 2023 | D32: =TEXT(Table2[[#This Row],[Date]],"mmmm") -> September | E32: David | F32: East | G32: Germany | H32: New York | I32: Sports | J32: T-Shirt | K32: Distributor | L32: Rep E | M32: 825.37 | N32: 11 | O32: 0.09 | P32: =IF(Table2[[#This Row],[Discount]]>20%,"HIGH","LOW") -> LOW | Q32: 8261.95 | R32: =_xlfn.IFS(Table2[[#This Row],[Revenue]]<1000,"Small",OR(Table2[[#This Row],[Revenue]]>1000,Table2[[#This Row],[Revenue]]<=5000),"Medium",Table2[[#This Row],[Revenue]]>5000,"Large") -> Medium | S32: =IF(Table2[[#This Row],[Revenue]]>3000,"Premium","Not Premium") -> Premium | T32: 6670.56 | U32: 1591.39 | V32: PayPal | W32: Critical | X32: Express | Y32: 42.08 | Z32: 8 | AA32: =IF(Table2[[#This Row],[DeliveryDays]]<=3,"FAST DELIVERY","LATE DELIVERY") -> LATE DELIVERY | AB32: Corporate | AC32: No | AD32: 1 | AE32: =_xlfn.IFS(Table2[[#This Row],[Rating]]=5,"Excellent",Table2[[#This Row],[Rating]]=4,"Good",Table2[[#This Row],[Rating]]=3,"Average",Table2[[#This Row],[Rating]]<=2,"Poor") -> Poor | AF32: =Table2[[#This Row],[Cost]]+Table2[[#This Row],[Profit]]+Table2[[#This Row],[ShippingCost]]+Table2[[#This Row],[DeliveryDays]] -> 8312.03 | AG32: =Table2[[#This Row],[Profit]]/Table2[[#This Row],[Cost]] -> 0.23856918
A33: 32 | B33: 2023-03-27 | C33: =YEAR(Table2[[#This Row],[Date]]) -> 2023 | D33: =TEXT(Table2[[#This Row],[Date]],"mmmm") -> March | E33: Amit | F33: West | G33: UK | H33: Toronto | I33: Clothing | J33: Laptop | K33: Retail | L33: Rep B | M33: 108.96 | N33: 14 | O33: 0.14 | P33: =IF(Table2[[#This Row],[Discount]]>20%,"HIGH","LOW") -> LOW | Q33: 1311.88 | R33: =_xlfn.IFS(Table2[[#This Row],[Revenue]]<1000,"Small",OR(Table2[[#This Row],[Revenue]]>1000,Table2[[#This Row],[Revenue]]<=5000),"Medium",Table2[[#This Row],[Revenue]]>5000,"Large") -> Medium | S33: =IF(Table2[[#This Row],[Revenue]]>3000,"Premium","Not Premium") -> Not Premium | T33: 872.57 | U33: 439.31 | V33: Credit Card | W33: Low | X33: Standard | Y33: 14.45 | Z33: 2 | AA33: =IF(Table2[[#This Row],[DeliveryDays]]<=3,"FAST DELIVERY","LATE DELIVERY") -> FAST DELIVERY | AB33: Consumer | AC33: No | AD33: 5 | AE33: =_xlfn.IFS(Table2[[#This Row],[Rating]]=5,"Excellent",Table2[[#This Row],[Rating]]=4,"Good",Table2[[#This Row],[Rating]]=3,"Average",Table2[[#This Row],[Rating]]<=2,"Poor") -> Excellent | AF33: =Table2[[#This Row],[Cost]]+Table2[[#This Row],[Profit]]+Table2[[#This Row],[ShippingCost]]+Table2[[#This Row],[DeliveryDays]] -> 1328.33 | AG33: =Table2[[#This Row],[Profit]]/Table2[[#This Row],[Cost]] -> 0.50346677 | AQ33: ProductCategory
A34: 33 | B34: 2024-03-16 | C34: =YEAR(Table2[[#This Row],[Date]]) -> 2024 | D34: =TEXT(Table2[[#This Row],[Date]],"mmmm") -> March | E34: Arjun | F34: West | G34: India | H34: New York | I34: Furniture | J34: Jacket | K34: Distributor | L34: Rep D | M34: 103.94 | N34: 4 | O34: 0.15 | P34: =IF(Table2[[#This Row],[Discount]]>20%,"HIGH","LOW") -> LOW | Q34: 353.4 | R34: =_xlfn.IFS(Table2[[#This Row],[Revenue]]<1000,"Small",OR(Table2[[#This Row],[Revenue]]>1000,Table2[[#This Row],[Revenue]]<=5000),"Medium",Table2[[#This Row],[Revenue]]>5000,"Large") -> Small | S34: =IF(Table2[[#This Row],[Revenue]]>3000,"Premium","Not Premium") -> Not Premium | T34: 206.51 | U34: 146.89 | V34: Credit Card | W34: Low | X34: Same Day | Y34: 29.93 | Z34: 3 | AA34: =IF(Table2[[#This Row],[DeliveryDays]]<=3,"FAST DELIVERY","LATE DELIVERY") -> FAST DELIVERY | AB34: Corporate | AC34: Yes | AD34: 5 | AE34: =_xlfn.IFS(Table2[[#This Row],[Rating]]=5,"Excellent",Table2[[#This Row],[Rating]]=4,"Good",Table2[[#This Row],[Rating]]=3,"Average",Table2[[#This Row],[Rating]]<=2,"Poor") -> Excellent | AF34: =Table2[[#This Row],[Cost]]+Table2[[#This Row],[Profit]]+Table2[[#This Row],[ShippingCost]]+Table2[[#This Row],[DeliveryDays]] -> 386.33 | AG34: =Table2[[#This Row],[Profit]]/Table2[[#This Row],[Cost]] -> 0.71129727 | AQ34: Electronics
A35: 34 | B35: 2024-01-07 | C35: =YEAR(Table2[[#This Row],[Date]]) -> 2024 | D35: =TEXT(Table2[[#This Row],[Date]],"mmmm") -> January | E35: Neha | F35: East | G35: Australia | H35: New York | I35: Sports | J35: Laptop | K35: Distributor | L35: Rep D | M35: 734.65 | N35: 18 | O35: 0.13 | P35: =IF(Table2[[#This Row],[Discount]]>20%,"HIGH","LOW") -> LOW | Q35: 11504.62 | R35: =_xlfn.IFS(Table2[[#This Row],[Revenue]]<1000,"Small",OR(Table2[[#This Row],[Revenue]]>1000,Table2[[#This Row],[Revenue]]<=5000),"Medium",Table2[[#This Row],[Revenue]]>5000,"Large") -> Medium | S35: =IF(Table2[[#This Row],[Revenue]]>3000,"Premium","Not Premium") -> Premium | T35: 9351.84 | U35: 2152.78 | V35: UPI | W35: Low | X35: Same Day | Y35: 41.95 | Z35: 2 | AA35: =IF(Table2[[#This Row],[DeliveryDays]]<=3,"FAST DELIVERY","LATE DELIVERY") -> FAST DELIVERY | AB35: Corporate | AC35: No | AD35: 2 | AE35: =_xlfn.IFS(Table2[[#This Row],[Rating]]=5,"Excellent",Table2[[#This Row],[Rating]]=4,"Good",Table2[[#This Row],[Rating]]=3,"Average",Table2[[#This Row],[Rating]]<=2,"Poor") -> Poor | AF35: =Table2[[#This Row],[Cost]]+Table2[[#This Row],[Profit]]+Table2[[#This Row],[ShippingCost]]+Table2[[#This Row],[DeliveryDays]] -> 11548.57 | AG35: =Table2[[#This Row],[Profit]]/Table2[[#This Row],[Cost]] -> 0.23019855 | BO35: Month
A36: 35 | B36: 2023-12-21 | C36: =YEAR(Table2[[#This Row],[Date]]) -> 2023 | D36: =TEXT(Table2[[#This Row],[Date]],"mmmm") -> December | E36: John | F36: South | G36: Australia | H36: Pune | I36: Office Supplies | J36: Desk | K36: Retail | L36: Rep B | M36: 320.13 | N36: 16 | O36: 0.28 | P36: =IF(Table2[[#This Row],[Discount]]>20%,"HIGH","LOW") -> HIGH | Q36: 3687.9 | R36: =_xlfn.IFS(Table2[[#This Row],[Revenue]]<1000,"Small",OR(Table2[[#This Row],[Revenue]]>1000,Table2[[#This Row],[Revenue]]<=5000),"Medium",Table2[[#This Row],[Revenue]]>5000,"Large") -> Medium | S36: =IF(Table2[[#This Row],[Revenue]]>3000,"Premium","Not Premium") -> Premium | T36: 2965.44 | U36: 722.46 | V36: PayPal | W36: Medium | X36: Standard | Y36: 9.33 | Z36: 8 | AA36: =IF(Table2[[#This Row],[DeliveryDays]]<=3,"FAST DELIVERY","LATE DELIVERY") -> LATE DELIVERY | AB36: Consumer | AC36: Yes | AD36: 4 | AE36: =_xlfn.IFS(Table2[[#This Row],[Rating]]=5,"Excellent",Table2[[#This Row],[Rating]]=4,"Good",Table2[[#This Row],[Rating]]=3,"Average",Table2[[#This Row],[Rating]]<=2,"Poor") -> Good | AF36: =Table2[[#This Row],[Cost]]+Table2[[#This Row],[Profit]]+Table2[[#This Row],[ShippingCost]]+Table2[[#This Row],[DeliveryDays]] -> 3705.23 | AG36: =Table2[[#This Row],[Profit]]/Table2[[#This Row],[Cost]] -> 0.24362658 | AQ36: OrderID | AR36: Date | AS36: CustomerName | AT36: Region | AU36: Country | AV36: City | AW36: ProductCategory | AX36: ProductName | AY36: SalesChannel | AZ36: SalesRep | BA36: UnitPrice | BB36: Quantity | BC36: Discount | BD36: Revenue | BE36: Cost | BF36: Profit | BG36: PaymentMethod | BH36: OrderPriority | BI36: ShipMode | BJ36: ShippingCost | BK36: DeliveryDays | BL36: CustomerSegment | BM36: Returned | BN36: Rating | BO36: 8
A37: 36 | B37: 2024-03-01 | C37: =YEAR(Table2[[#This Row],[Date]]) -> 2024 | D37: =TEXT(Table2[[#This Row],[Date]],"mmmm") -> March | E37: Michael | F37: South | G37: USA | H37: Mumbai | I37: Sports | J37: Keyboard | K37: Retail | L37: Rep D | M37: 478.26 | N37: 8 | O37: 0.1 | P37: =IF(Table2[[#This Row],[Discount]]>20%,"HIGH","LOW") -> LOW | Q37: 3443.47 | R37: =_xlfn.IFS(Table2[[#This Row],[Revenue]]<1000,"Small",OR(Table2[[#This Row],[Revenue]]>1000,Table2[[#This Row],[Revenue]]<=5000),"Medium",Table2[[#This Row],[Revenue]]>5000,"Large") -> Medium | S37: =IF(Table2[[#This Row],[Revenue]]>3000,"Premium","Not Premium") -> Premium | T37: 2982.16 | U37: 461.31 | V37: Bank Transfer | W37: Critical | X37: Express | Y37: 13.54 | Z37: 7 | AA37: =IF(Table2[[#This Row],[DeliveryDays]]<=3,"FAST DELIVERY","LATE DELIVERY") -> LATE DELIVERY | AB37: Consumer | AC37: No | AD37: 1 | AE37: =_xlfn.IFS(Table2[[#This Row],[Rating]]=5,"Excellent",Table2[[#This Row],[Rating]]=4,"Good",Table2[[#This Row],[Rating]]=3,"Average",Table2[[#This Row],[Rating]]<=2,"Poor") -> Poor | AF37: =Table2[[#This Row],[Cost]]+Table2[[#This Row],[Profit]]+Table2[[#This Row],[ShippingCost]]+Table2[[#This Row],[DeliveryDays]] -> 3464.01 | AG37: =Table2[[#This Row],[Profit]]/Table2[[#This Row],[Cost]] -> 0.15468989 | AQ37: 1 | AR37: 2023-08-26 | AS37: Michael | AT37: North | AU37: Canada | AV37: Mumbai | AW37: Electronics | AX37: Jacket | AY37: Retail | AZ37: Rep D | BA37: 576.66 | BB37: 4 | BC37: 0.17 | BD37: 1914.51 | BE37: 1118.63 | BF37: 795.88 | BG37: Bank Transfer | BH37: Medium | BI37: Standard | BJ37: 32.48 | BK37: 10 | BL37: Home Office | BM37: No | BN37: 2 | BO37: 10
A38: 37 | B38: 2024-05-02 | C38: =YEAR(Table2[[#This Row],[Date]]) -> 2024 | D38: =TEXT(Table2[[#This Row],[Date]],"mmmm") -> May | E38: Arjun | F38: South | G38: USA | H38: Delhi | I38: Electronics | J38: T-Shirt | K38: Retail | L38: Rep D | M38: 423.11 | N38: 20 | O38: 0.23 | P38: =IF(Table2[[#This Row],[Discount]]>20%,"HIGH","LOW") -> HIGH | Q38: 6515.89 | R38: =_xlfn.IFS(Table2[[#This Row],[Revenue]]<1000,"Small",OR(Table2[[#This Row],[Revenue]]>1000,Table2[[#This Row],[Revenue]]<=5000),"Medium",Table2[[#This Row],[Revenue]]>5000,"Large") -> Medium | S38: =IF(Table2[[#This Row],[Revenue]]>3000,"Premium","Not Premium") -> Premium | T38: 4640.04 | U38: 1875.85 | V38: Cash | W38: Medium | X38: Same Day | Y38: 31.13 | Z38: 8 | AA38: =IF(Table2[[#This Row],[DeliveryDays]]<=3,"FAST DELIVERY","LATE DELIVERY") -> LATE DELIVERY | AB38: Home Office | AC38: No | AD38: 5 | AE38: =_xlfn.IFS(Table2[[#This Row],[Rating]]=5,"Excellent",Table2[[#This Row],[Rating]]=4,"Good",Table2[[#This Row],[Rating]]=3,"Average",Table2[[#This Row],[Rating]]<=2,"Poor") -> Excellent | AF38: =Table2[[#This Row],[Cost]]+Table2[[#This Row],[Profit]]+Table2[[#This Row],[ShippingCost]]+Table2[[#This Row],[DeliveryDays]] -> 6555.02 | AG38: =Table2[[#This Row],[Profit]]/Table2[[#This Row],[Cost]] -> 0.40427453 | AQ38: 2 | AR38: 2024-10-15 | AS38: Priya | AT38: South | AU38: USA | AV38: Berlin | AW38: Electronics | AX38: Jacket | AY38: Online | AZ38: Rep C | BA38: 447.27 | BB38: 5 | BC38: 0.12 | BD38: 1967.99 | BE38: 1337.43 | BF38: 630.56 | BG38: Credit Card | BH38: Medium | BI38: Same Day | BJ38: 25.58 | BK38: 4 | BL38: Home Office | BM38: No | BN38: 1 | BO38: 6
A39: 38 | B39: 2024-10-31 | C39: =YEAR(Table2[[#This Row],[Date]]) -> 2024 | D39: =TEXT(Table2[[#This Row],[Date]],"mmmm") -> October | E39: Riya | F39: South | G39: India | H39: Toronto | I39: Clothing | J39: T-Shirt | K39: Online | L39: Rep D | M39: 804.65 | N39: 5 | O39: 0.13 | P39: =IF(Table2[[#This Row],[Discount]]>20%,"HIGH","LOW") -> LOW | Q39: 3500.23 | R39: =_xlfn.IFS(Table2[[#This Row],[Revenue]]<1000,"Small",OR(Table2[[#This Row],[Revenue]]>1000,Table2[[#This Row],[Revenue]]<=5000),"Medium",Table2[[#This Row],[Revenue]]>5000,"Large") -> Medium | S39: =IF(Table2[[#This Row],[Revenue]]>3000,"Premium","Not Premium") -> Premium | T39: 2149.83 | U39: 1350.4 | V39: PayPal | W39: Low | X39: Express | Y39: 11.72 | Z39: 1 | AA39: =IF(Table2[[#This Row],[DeliveryDays]]<=3,"FAST DELIVERY","LATE DELIVERY") -> FAST DELIVERY | AB39: Home Office | AC39: Yes | AD39: 2 | AE39: =_xlfn.IFS(Table2[[#This Row],[Rating]]=5,"Excellent",Table2[[#This Row],[Rating]]=4,"Good",Table2[[#This Row],[Rating]]=3,"Average",Table2[[#This Row],[Rating]]<=2,"Poor") -> Poor | AF39: =Table2[[#This Row],[Cost]]+Table2[[#This Row],[Profit]]+Table2[[#This Row],[ShippingCost]]+Table2[[#This Row],[DeliveryDays]] -> 3512.95 | AG39: =Table2[[#This Row],[Profit]]/Table2[[#This Row],[Cost]] -> 0.62814269 | AQ39: 15 | AR39: 2023-06-14 | AS39: Priya | AT39: South | AU39: Canada | AV39: London | AW39: Electronics | AX39: T-Shirt | AY39: Distributor | AZ39: Rep E | BA39: 66.03 | BB39: 4 | BC39: 0.03 | BD39: 256.2 | BE39: 228.6 | BF39: 27.6 | BG39: Bank Transfer | BH39: Low | BI39: Same Day | BJ39: 18.99 | BK39: 4 | BL39: Consumer | BM39: Yes | BN39: 3 | BO39: 12
A40: 39 | B40: 2023-06-11 | C40: =YEAR(Table2[[#This Row],[Date]]) -> 2023 | D40: =TEXT(Table2[[#This Row],[Date]],"mmmm") -> June | E40: Michael | F40: East | G40: Canada | H40: Sydney | I40: Furniture | J40: Monitor | K40: Online | L40: Rep A | M40: 136.05 | N40: 4 | O40: 0.1 | P40: =IF(Table2[[#This Row],[Discount]]>20%,"HIGH","LOW") -> LOW | Q40: 489.78 | R40: =_xlfn.IFS(Table2[[#This Row],[Revenue]]<1000,"Small",OR(Table2[[#This Row],[Revenue]]>1000,Table2[[#This Row],[Revenue]]<=5000),"Medium",Table2[[#This Row],[Revenue]]>5000,"Large") -> Small | S40: =IF(Table2[[#This Row],[Revenue]]>3000,"Premium","Not Premium") -> Not Premium | T40: 257.22 | U40: 232.56 | V40: Credit Card | W40: Low | X40: Standard | Y40: 7.33 | Z40: 6 | AA40: =IF(Table2[[#This Row],[DeliveryDays]]<=3,"FAST DELIVERY","LATE DELIVERY") -> LATE DELIVERY | AB40: Consumer | AC40: Yes | AD40: 4 | AE40: =_xlfn.IFS(Table2[[#This Row],[Rating]]=5,"Excellent",Table2[[#This Row],[Rating]]=4,"Good",Table2[[#This Row],[Rating]]=3,"Average",Table2[[#This Row],[Rating]]<=2,"Poor") -> Good | AF40: =Table2[[#This Row],[Cost]]+Table2[[#This Row],[Profit]]+Table2[[#This Row],[ShippingCost]]+Table2[[#This Row],[DeliveryDays]] -> 503.11 | AG40: =Table2[[#This Row],[Profit]]/Table2[[#This Row],[Cost]] -> 0.90412876 | AQ40: 19 | AR40: 2024-12-27 | AS40: Sara | AT40: East | AU40: USA | AV40: Mumbai | AW40: Electronics | AX40: Printer | AY40: Distributor | AZ40: Rep C | BA40: 592.47 | BB40: 19 | BC40: 0.08 | BD40: 10356.38 | BE40: 8696.16 | BF40: 1660.22 | BG40: PayPal | BH40: Critical | BI40: Standard | BJ40: 16.1 | BK40: 3 | BL40: Consumer | BM40: Yes | BN40: 5 | BO40: 11
A41: 40 | B41: 2024-06-20 | C41: =YEAR(Table2[[#This Row],[Date]]) -> 2024 | D41: =TEXT(Table2[[#This Row],[Date]],"mmmm") -> June | E41: Rahul | F41: East | G41: UK | H41: New York | I41: Electronics | J41: Laptop | K41: Retail | L41: Rep D | M41: 552.36 | N41: 8 | O41: 0.25 | P41: =IF(Table2[[#This Row],[Discount]]>20%,"HIGH","LOW") -> HIGH | Q41: 3314.16 | R41: =_xlfn.IFS(Table2[[#This Row],[Revenue]]<1000,"Small",OR(Table2[[#This Row],[Revenue]]>1000,Table2[[#This Row],[Revenue]]<=5000),"Medium",Table2[[#This Row],[Revenue]]>5000,"Large") -> Medium | S41: =IF(Table2[[#This Row],[Revenue]]>3000,"Premium","Not Premium") -> Premium | T41: 2498.48 | U41: 815.68 | V41: PayPal | W41: High | X41: Express | Y41: 39.93 | Z41: 5 | AA41: =IF(Table2[[#This Row],[DeliveryDays]]<=3,"FAST DELIVERY","LATE DELIVERY") -> LATE DELIVERY | AB41: Consumer | AC41: Yes | AD41: 3 | AE41: =_xlfn.IFS(Table2[[#This Row],[Rating]]=5,"Excellent",Table2[[#This Row],[Rating]]=4,"Good",Table2[[#This Row],[Rating]]=3,"Average",Table2[[#This Row],[Rating]]<=2,"Poor") -> Average | AF41: =Table2[[#This Row],[Cost]]+Table2[[#This Row],[Profit]]+Table2[[#This Row],[ShippingCost]]+Table2[[#This Row],[DeliveryDays]] -> 3359.09 | AG41: =Table2[[#This Row],[Profit]]/Table2[[#This Row],[Cost]] -> 0.32647049 | AQ41: 22 | AR41: 2024-11-14 | AS41: Sara | AT41: South | AU41: Canada | AV41: Mumbai | AW41: Electronics | AX41: Football | AY41: Online | AZ41: Rep C | BA41: 433.56 | BB41: 16 | BC41: 0.08 | BD41: 6382 | BE41: 4078.68 | BF41: 2303.32 | BG41: Cash | BH41: Medium | BI41: Same Day | BJ41: 5.44 | BK41: 8 | BL41: Consumer | BM41: No | BN41: 2 | BO41: 8
A42: 41 | B42: 2023-04-21 | C42: =YEAR(Table2[[#This Row],[Date]]) -> 2023 | D42: =TEXT(Table2[[#This Row],[Date]],"mmmm") -> April | E42: David | F42: South | G42: UK | H42: Berlin | I42: Clothing | J42: Football | K42: Distributor | L42: Rep C | M42: 452.08 | N42: 19 | O42: 0.24 | P42: =IF(Table2[[#This Row],[Discount]]>20%,"HIGH","LOW") -> HIGH | Q42: 6528.04 | R42: =_xlfn.IFS(Table2[[#This Row],[Revenue]]<1000,"Small",OR(Table2[[#This Row],[Revenue]]>1000,Table2[[#This Row],[Revenue]]<=5000),"Medium",Table2[[#This Row],[Revenue]]>5000,"Large") -> Medium | S42: =IF(Table2[[#This Row],[Revenue]]>3000,"Premium","Not Premium") -> Premium | T42: 5864.42 | U42: 663.62 | V42: Bank Transfer | W42: Low | X42: Standard | Y42: 15.25 | Z42: 6 | AA42: =IF(Table2[[#This Row],[DeliveryDays]]<=3,"FAST DELIVERY","LATE DELIVERY") -> LATE DELIVERY | AB42: Corporate | AC42: No | AD42: 1 | AE42: =_xlfn.IFS(Table2[[#This Row],[Rating]]=5,"Excellent",Table2[[#This Row],[Rating]]=4,"Good",Table2[[#This Row],[Rating]]=3,"Average",Table2[[#This Row],[Rating]]<=2,"Poor") -> Poor | AF42: =Table2[[#This Row],[Cost]]+Table2[[#This Row],[Profit]]+Table2[[#This Row],[ShippingCost]]+Table2[[#This Row],[DeliveryDays]] -> 6549.29 | AG42: =Table2[[#This Row],[Profit]]/Table2[[#This Row],[Cost]] -> 0.11316038 | AQ42: 25 | AR42: 2024-08-24 | AS42: Priya | AT42: South | AU42: Germany | AV42: Delhi | AW42: Electronics | AX42: T-Shirt | AY42: Retail | AZ42: Rep B | BA42: 823.06 | BB42: 6 | BC42: 0.1 | BD42: 4444.52 | BE42: 3447.91 | BF42: 996.61 | BG42: PayPal | BH42: Medium | BI42: Express | BJ42: 10.2 | BK42: 1 | BL42: Consumer | BM42: Yes | BN42: 5 | BO42: 4
A43: 42 | B43: 2024-03-16 | C43: =YEAR(Table2[[#This Row],[Date]]) -> 2024 | D43: =TEXT(Table2[[#This Row],[Date]],"mmmm") -> March | E43: Sara | F43: North | G43: Australia | H43: Mumbai | I43: Furniture | J43: T-Shirt | K43: Distributor | L43: Rep C | M43: 315.51 | N43: 11 | O43: 0.03 | P43: =IF(Table2[[#This Row],[Discount]]>20%,"HIGH","LOW") -> LOW | Q43: 3366.49 | R43: =_xlfn.IFS(Table2[[#This Row],[Revenue]]<1000,"Small",OR(Table2[[#This Row],[Revenue]]>1000,Table2[[#This Row],[Revenue]]<=5000),"Medium",Table2[[#This Row],[Revenue]]>5000,"Large") -> Medium | S43: =IF(Table2[[#This Row],[Revenue]]>3000,"Premium","Not Premium") -> Premium | T43: 1769.82 | U43: 1596.67 | V43: PayPal | W43: Medium | X43: Standard | Y43: 42.55 | Z43: 10 | AA43: =IF(Table2[[#This Row],[DeliveryDays]]<=3,"FAST DELIVERY","LATE DELIVERY") -> LATE DELIVERY | AB43: Corporate | AC43: Yes | AD43: 4 | AE43: =_xlfn.IFS(Table2[[#This Row],[Rating]]=5,"Excellent",Table2[[#This Row],[Rating]]=4,"Good",Table2[[#This Row],[Rating]]=3,"Average",Table2[[#This Row],[Rating]]<=2,"Poor") -> Good | AF43: =Table2[[#This Row],[Cost]]+Table2[[#This Row],[Profit]]+Table2[[#This Row],[ShippingCost]]+Table2[[#This Row],[DeliveryDays]] -> 3419.04 | AG43: =Table2[[#This Row],[Profit]]/Table2[[#This Row],[Cost]] -> 0.90216519 | AQ43: 27 | AR43: 2023-04-27 | AS43: Arjun | AT43: North | AU43: India | AV43: New York | AW43: Electronics | AX43: Football | AY43: Online | AZ43: Rep E | BA43: 600.43 | BB43: 17 | BC43: 0.17 | BD43: 8472.07 | BE43: 4854.92 | BF43: 3617.15 | BG43: Credit Card | BH43: Low | BI43: Same Day | BJ43: 12.96 | BK43: 6 | BL43: Home Office | BM43: Yes | BN43: 5 | BO43: 5
A44: 43 | B44: 2024-12-16 | C44: =YEAR(Table2[[#This Row],[Date]]) -> 2024 | D44: =TEXT(Table2[[#This Row],[Date]],"mmmm") -> December | E44: Arjun | F44: South | G44: Germany | H44: New York | I44: Electronics | J44: Monitor | K44: Online | L44: Rep E | M44: 854.24 | N44: 2 | O44: 0.14 | P44: =IF(Table2[[#This Row],[Discount]]>20%,"HIGH","LOW") -> LOW | Q44: 1469.29 | R44: =_xlfn.IFS(Table2[[#This Row],[Revenue]]<1000,"Small",OR(Table2[[#This Row],[Revenue]]>1000,Table2[[#This Row],[Revenue]]<=5000),"Medium",Table2[[#This Row],[Revenue]]>5000,"Large") -> Medium | S44: =IF(Table2[[#This Row],[Revenue]]>3000,"Premium","Not Premium") -> Not Premium | T44: 1206.28 | U44: 263.01 | V44: PayPal | W44: Critical | X44: Express | Y44: 25.79 | Z44: 9 | AA44: =IF(Table2[[#This Row],[DeliveryDays]]<=3,"FAST DELIVERY","LATE DELIVERY") -> LATE DELIVERY | AB44: Home Office | AC44: No | AD44: 5 | AE44: =_xlfn.IFS(Table2[[#This Row],[Rating]]=5,"Excellent",Table2[[#This Row],[Rating]]=4,"Good",Table2[[#This Row],[Rating]]=3,"Average",Table2[[#This Row],[Rating]]<=2,"Poor") -> Excellent | AF44: =Table2[[#This Row],[Cost]]+Table2[[#This Row],[Profit]]+Table2[[#This Row],[ShippingCost]]+Table2[[#This Row],[DeliveryDays]] -> 1504.08 | AG44: =Table2[[#This Row],[Profit]]/Table2[[#This Row],[Cost]] -> 0.21803396 | AQ44: 28 | AR44: 2023-05-19 | AS44: Amit | AT44: North | AU44: India | AV44: Toronto | AW44: Electronics | AX44: T-Shirt | AY44: Retail | AZ44: Rep D | BA44: 697.99 | BB44: 7 | BC44: 0.1 | BD44: 4397.34 | BE44: 2823.58 | BF44: 1573.76 | BG44: UPI | BH44: Critical | BI44: Same Day | BJ44: 27.37 | BK44: 1 | BL44: Consumer | BM44: Yes | BN44: 5 | BO44: 7
A45: 44 | B45: 2024-06-07 | C45: =YEAR(Table2[[#This Row],[Date]]) -> 2024 | D45: =TEXT(Table2[[#This Row],[Date]],"mmmm") -> June | E45: Rahul | F45: West | G45: Germany | H45: Mumbai | I45: Electronics | J45: Laptop | K45: Online | L45: Rep E | M45: 613.93 | N45: 19 | O45: 0.22 | P45: =IF(Table2[[#This Row],[Discount]]>20%,"HIGH","LOW") -> HIGH | Q45: 9098.44 | R45: =_xlfn.IFS(Table2[[#This Row],[Revenue]]<1000,"Small",OR(Table2[[#This Row],[Revenue]]>1000,Table2[[#This Row],[Revenue]]<=5000),"Medium",Table2[[#This Row],[Revenue]]>5000,"Large") -> Medium | S45: =IF(Table2[[#This Row],[Revenue]]>3000,"Premium","Not Premium") -> Premium | T45: 5865.98 | U45: 3232.46 | V45: UPI | W45: Critical | X45: Standard | Y45: 13.92 | Z45: 2 | AA45: =IF(Table2[[#This Row],[DeliveryDays]]<=3,"FAST DELIVERY","LATE DELIVERY") -> FAST DELIVERY | AB45: Consumer | AC45: No | AD45: 3 | AE45: =_xlfn.IFS(Table2[[#This Row],[Rating]]=5,"Excellent",Table2[[#This Row],[Rating]]=4,"Good",Table2[[#This Row],[Rating]]=3,"Average",Table2[[#This Row],[Rating]]<=2,"Poor") -> Average | AF45: =Table2[[#This Row],[Cost]]+Table2[[#This Row],[Profit]]+Table2[[#This Row],[ShippingCost]]+Table2[[#This Row],[DeliveryDays]] -> 9114.36 | AG45: =Table2[[#This Row],[Profit]]/Table2[[#This Row],[Cost]] -> 0.551052 | AQ45: 29 | AR45: 2024-07-30 | AS45: Arjun | AT45: East | AU45: UK | AV45: Sydney | AW45: Electronics | AX45: Laptop | AY45: Online | AZ45: Rep E | BA45: 701.56 | BB45: 3 | BC45: 0.14 | BD45: 1810.02 | BE45: 1148.8 | BF45: 661.22 | BG45: PayPal | BH45: High | BI45: Standard | BJ45: 37.53 | BK45: 7 | BL45: Corporate | BM45: No | BN45: 3 | BO45: 5
A46: 45 | B46: 2024-03-03 | C46: =YEAR(Table2[[#This Row],[Date]]) -> 2024 | D46: =TEXT(Table2[[#This Row],[Date]],"mmmm") -> March | E46: Michael | F46: West | G46: Germany | H46: Mumbai | I46: Sports | J46: Keyboard | K46: Retail | L46: Rep D | M46: 311 | N46: 12 | O46: 0.13 | P46: =IF(Table2[[#This Row],[Discount]]>20%,"HIGH","LOW") -> LOW | Q46: 3246.84 | R46: =_xlfn.IFS(Table2[[#This Row],[Revenue]]<1000,"Small",OR(Table2[[#This Row],[Revenue]]>1000,Table2[[#This Row],[Revenue]]<=5000),"Medium",Table2[[#This Row],[Revenue]]>5000,"Large") -> Medium | S46: =IF(Table2[[#This Row],[Revenue]]>3000,"Premium","Not Premium") -> Premium | T46: 2312.81 | U46: 934.03 | V46: Credit Card | W46: Medium | X46: Express | Y46: 27.25 | Z46: 6 | AA46: =IF(Table2[[#This Row],[DeliveryDays]]<=3,"FAST DELIVERY","LATE DELIVERY") -> LATE DELIVERY | AB46: Consumer | AC46: No | AD46: 3 | AE46: =_xlfn.IFS(Table2[[#This Row],[Rating]]=5,"Excellent",Table2[[#This Row],[Rating]]=4,"Good",Table2[[#This Row],[Rating]]=3,"Average",Table2[[#This Row],[Rating]]<=2,"Poor") -> Average | AF46: =Table2[[#This Row],[Cost]]+Table2[[#This Row],[Profit]]+Table2[[#This Row],[ShippingCost]]+Table2[[#This Row],[DeliveryDays]] -> 3280.09 | AG46: =Table2[[#This Row],[Profit]]/Table2[[#This Row],[Cost]] -> 0.40385073 | AQ46: 37 | AR46: 2024-05-02 | AS46: Arjun | AT46: South | AU46: USA | AV46: Delhi | AW46: Electronics | AX46: T-Shirt | AY46: Retail | AZ46: Rep D | BA46: 423.11 | BB46: 20 | BC46: 0.23 | BD46: 6515.89 | BE46: 4640.04 | BF46: 1875.85 | BG46: Cash | BH46: Medium | BI46: Same Day | BJ46: 31.13 | BK46: 8 | BL46: Home Office | BM46: No | BN46: 5 | BO46: 6
A47: 46 | B47: 2023-06-17 | C47: =YEAR(Table2[[#This Row],[Date]]) -> 2023 | D47: =TEXT(Table2[[#This Row],[Date]],"mmmm") -> June | E47: Michael | F47: North | G47: India | H47: Mumbai | I47: Furniture | J47: Printer | K47: Distributor | L47: Rep D | M47: 256.77 | N47: 16 | O47: 0.23 | P47: =IF(Table2[[#This Row],[Discount]]>20%,"HIGH","LOW") -> HIGH | Q47: 3163.41 | R47: =_xlfn.IFS(Table2[[#This Row],[Revenue]]<1000,"Small",OR(Table2[[#This Row],[Revenue]]>1000,Table2[[#This Row],[Revenue]]<=5000),"Medium",Table2[[#This Row],[Revenue]]>5000,"Large") -> Medium | S47: =IF(Table2[[#This Row],[Revenue]]>3000,"Premium","Not Premium") -> Premium | T47: 1847.04 | U47: 1316.37 | V47: UPI | W47: High | X47: Standard | Y47: 49.27 | Z47: 10 | AA47: =IF(Table2[[#This Row],[DeliveryDays]]<=3,"FAST DELIVERY","LATE DELIVERY") -> LATE DELIVERY | AB47: Consumer | AC47: Yes | AD47: 2 | AE47: =_xlfn.IFS(Table2[[#This Row],[Rating]]=5,"Excellent",Table2[[#This Row],[Rating]]=4,"Good",Table2[[#This Row],[Rating]]=3,"Average",Table2[[#This Row],[Rating]]<=2,"Poor") -> Poor | AF47: =Table2[[#This Row],[Cost]]+Table2[[#This Row],[Profit]]+Table2[[#This Row],[ShippingCost]]+Table2[[#This Row],[DeliveryDays]] -> 3222.68 | AG47: =Table2[[#This Row],[Profit]]/Table2[[#This Row],[Cost]] -> 0.71269166 | AQ47: 40 | AR47: 2024-06-20 | AS47: Rahul | AT47: East | AU47: UK | AV47: New York | AW47: Electronics | AX47: Laptop | AY47: Retail | AZ47: Rep D | BA47: 552.36 | BB47: 8 | BC47: 0.25 | BD47: 3314.16 | BE47: 2498.48 | BF47: 815.68 | BG47: PayPal | BH47: High | BI47: Express | BJ47: 39.93 | BK47: 5 | BL47: Consumer | BM47: Yes | BN47: 3 | BO47: 12
A48: 47 | B48: 2023-02-08 | C48: =YEAR(Table2[[#This Row],[Date]]) -> 2023 | D48: =TEXT(Table2[[#This Row],[Date]],"mmmm") -> February | E48: Neha | F48: West | G48: USA | H48: Sydney | I48: Clothing | J48: Desk | K48: Retail | L48: Rep D | M48: 911.31 | N48: 7 | O48: 0.15 | P48: =IF(Table2[[#This Row],[Discount]]>20%,"HIGH","LOW") -> LOW | Q48: 5422.29 | R48: =_xlfn.IFS(Table2[[#This Row],[Revenue]]<1000,"Small",OR(Table2[[#This Row],[Revenue]]>1000,Table2[[#This Row],[Revenue]]<=5000),"Medium",Table2[[#This Row],[Revenue]]>5000,"Large") -> Medium | S48: =IF(Table2[[#This Row],[Revenue]]>3000,"Premium","Not Premium") -> Premium | T48: 4626.36 | U48: 795.93 | V48: PayPal | W48: Low | X48: Same Day | Y48: 27.65 | Z48: 5 | AA48: =IF(Table2[[#This Row],[DeliveryDays]]<=3,"FAST DELIVERY","LATE DELIVERY") -> LATE DELIVERY | AB48: Consumer | AC48: Yes | AD48: 1 | AE48: =_xlfn.IFS(Table2[[#This Row],[Rating]]=5,"Excellent",Table2[[#This Row],[Rating]]=4,"Good",Table2[[#This Row],[Rating]]=3,"Average",Table2[[#This Row],[Rating]]<=2,"Poor") -> Poor | AF48: =Table2[[#This Row],[Cost]]+Table2[[#This Row],[Profit]]+Table2[[#This Row],[ShippingCost]]+Table2[[#This Row],[DeliveryDays]] -> 5454.94 | AG48: =Table2[[#This Row],[Profit]]/Table2[[#This Row],[Cost]] -> 0.17204238 | AQ48: 43 | AR48: 2024-12-16 | AS48: Arjun | AT48: South | AU48: Germany | AV48: New York | AW48: Electronics | AX48: Monitor | AY48: Online | AZ48: Rep E | BA48: 854.24 | BB48: 2 | BC48: 0.14 | BD48: 1469.29 | BE48: 1206.28 | BF48: 263.01 | BG48: PayPal | BH48: Critical | BI48: Express | BJ48: 25.79 | BK48: 9 | BL48: Home Office | BM48: No | BN48: 5 | BO48: 6
... A236: 235 | B236: 2023-01-08 | C236: =YEAR(Table2[[#This Row],[Date]]) -> 2023 | D236: =TEXT(Table2[[#This Row],[Date]],"mmmm") -> January | E236: Neha | F236: North | G236: UK | H236: Toronto | I236: Clothing | J236: T-Shirt | K236: Retail | L236: Rep A | M236: 335.12 | N236: 8 | O236: 0.07 | P236: =IF(Table2[[#This Row],[Discount]]>20%,"HIGH","LOW") -> LOW | Q236: 2493.29 | R236: =_xlfn.IFS(Table2[[#This Row],[Revenue]]<1000,"Small",OR(Table2[[#This Row],[Revenue]]>1000,Table2[[#This Row],[Revenue]]<=5000),"Medium",Table2[[#This Row],[Revenue]]>5000,"Large") -> Medium | S236: =IF(Table2[[#This Row],[Revenue]]>3000,"Premium","Not Premium") -> Not Premium | T236: 1323.58 | U236: 1169.71 | V236: PayPal | W236: High | X236: Same Day | Y236: 9.76 | Z236: 3 | AA236: =IF(Table2[[#This Row],[DeliveryDays]]<=3,"FAST DELIVERY","LATE DELIVERY") -> FAST DELIVERY | AB236: Consumer | AC236: No | AD236: 5 | AE236: =_xlfn.IFS(Table2[[#This Row],[Rating]]=5,"Excellent",Table2[[#This Row],[Rating]]=4,"Good",Table2[[#This Row],[Rating]]=3,"Average",Table2[[#This Row],[Rating]]<=2,"Poor") -> Excellent | AF236: =Table2[[#This Row],[Cost]]+Table2[[#This Row],[Profit]]+Table2[[#This Row],[ShippingCost]]+Table2[[#This Row],[DeliveryDays]] -> 2506.05 | AG236: =Table2[[#This Row],[Profit]]/Table2[[#This Row],[Cost]] -> 0.88374711 | AQ236: 987 | AR236: 2024-12-02 | AS236: Priya | AT236: North | AU236: USA | AV236: Delhi | AW236: Electronics | AX236: Football | AY236: Distributor | AZ236: Rep C | BA236: 894.32 | BB236: 16 | BC236: 0.21 | BD236: 11304.2 | BE236: 7840.89 | BF236: 3463.31 | BG236: Credit Card | BH236: Low | BI236: Express | BJ236: 5.99 | BK236: 9 | BL236: Home Office | BM236: Yes | BN236: 2 | BO236: 4
A237: 236 | B237: 2023-09-04 | C237: =YEAR(Table2[[#This Row],[Date]]) -> 2023 | D237: =TEXT(Table2[[#This Row],[Date]],"mmmm") -> September | E237: Neha | F237: West | G237: Germany | H237: Delhi | I237: Electronics | J237: Monitor | K237: Online | L237: Rep D | M237: 725.75 | N237: 5 | O237: 0.3 | P237: =IF(Table2[[#This Row],[Discount]]>20%,"HIGH","LOW") -> HIGH | Q237: 2540.12 | R237: =_xlfn.IFS(Table2[[#This Row],[Revenue]]<1000,"Small",OR(Table2[[#This Row],[Revenue]]>1000,Table2[[#This Row],[Revenue]]<=5000),"Medium",Table2[[#This Row],[Revenue]]>5000,"Large") -> Medium | S237: =IF(Table2[[#This Row],[Revenue]]>3000,"Premium","Not Premium") -> Not Premium | T237: 1834.91 | U237: 705.21 | V237: Cash | W237: Medium | X237: Same Day | Y237: 23.12 | Z237: 4 | AA237: =IF(Table2[[#This Row],[DeliveryDays]]<=3,"FAST DELIVERY","LATE DELIVERY") -> LATE DELIVERY | AB237: Corporate | AC237: Yes | AD237: 1 | AE237: =_xlfn.IFS(Table2[[#This Row],[Rating]]=5,"Excellent",Table2[[#This Row],[Rating]]=4,"Good",Table2[[#This Row],[Rating]]=3,"Average",Table2[[#This Row],[Rating]]<=2,"Poor") -> Poor | AF237: =Table2[[#This Row],[Cost]]+Table2[[#This Row],[Profit]]+Table2[[#This Row],[ShippingCost]]+Table2[[#This Row],[DeliveryDays]] -> 2567.24 | AG237: =Table2[[#This Row],[Profit]]/Table2[[#This Row],[Cost]] -> 0.38432948 | AQ237: 994 | AR237: 2023-04-14 | AS237: Sophia | AT237: East | AU237: Germany | AV237: Sydney | AW237: Electronics | AX237: Jacket | AY237: Retail | AZ237: Rep A | BA237: 789.68 | BB237: 11 | BC237: 0.02 | BD237: 8512.75 | BE237: 4347.32 | BF237: 4165.43 | BG237: UPI | BH237: High | BI237: Express | BJ237: 39.37 | BK237: 9 | BL237: Home Office | BM237: Yes | BN237: 5
A238: 237 | B238: 2023-08-23 | C238: =YEAR(Table2[[#This Row],[Date]]) -> 2023 | D238: =TEXT(Table2[[#This Row],[Date]],"mmmm") -> August | E238: David | F238: West | G238: USA | H238: Toronto | I238: Sports | J238: Laptop | K238: Retail | L238: Rep C | M238: 888.49 | N238: 11 | O238: 0.09 | P238: =IF(Table2[[#This Row],[Discount]]>20%,"HIGH","LOW") -> LOW | Q238: 8893.78 | R238: =_xlfn.IFS(Table2[[#This Row],[Revenue]]<1000,"Small",OR(Table2[[#This Row],[Revenue]]>1000,Table2[[#This Row],[Revenue]]<=5000),"Medium",Table2[[#This Row],[Revenue]]>5000,"Large") -> Medium | S238: =IF(Table2[[#This Row],[Revenue]]>3000,"Premium","Not Premium") -> Premium | T238: 7729.69 | U238: 1164.09 | V238: Cash | W238: Low | X238: Standard | Y238: 42.01 | Z238: 2 | AA238: =IF(Table2[[#This Row],[DeliveryDays]]<=3,"FAST DELIVERY","LATE DELIVERY") -> FAST DELIVERY | AB238: Corporate | AC238: Yes | AD238: 1 | AE238: =_xlfn.IFS(Table2[[#This Row],[Rating]]=5,"Excellent",Table2[[#This Row],[Rating]]=4,"Good",Table2[[#This Row],[Rating]]=3,"Average",Table2[[#This Row],[Rating]]<=2,"Poor") -> Poor | AF238: =Table2[[#This Row],[Cost]]+Table2[[#This Row],[Profit]]+Table2[[#This Row],[ShippingCost]]+Table2[[#This Row],[DeliveryDays]] -> 8937.79 | AG238: =Table2[[#This Row],[Profit]]/Table2[[#This Row],[Cost]] -> 0.15059983
A239: 238 | B239: 2023-10-01 | C239: =YEAR(Table2[[#This Row],[Date]]) -> 2023 | D239: =TEXT(Table2[[#This Row],[Date]],"mmmm") -> October | E239: Amit | F239: East | G239: Germany | H239: Pune | I239: Office Supplies | J239: Tablet | K239: Online | L239: Rep E | M239: 908.86 | N239: 12 | O239: 0.04 | P239: =IF(Table2[[#This Row],[Discount]]>20%,"HIGH","LOW") -> LOW | Q239: 10470.07 | R239: =_xlfn.IFS(Table2[[#This Row],[Revenue]]<1000,"Small",OR(Table2[[#This Row],[Revenue]]>1000,Table2[[#This Row],[Revenue]]<=5000),"Medium",Table2[[#This Row],[Revenue]]>5000,"Large") -> Medium | S239: =IF(Table2[[#This Row],[Revenue]]>3000,"Premium","Not Premium") -> Premium | T239: 8845.52 | U239: 1624.55 | V239: Credit Card | W239: High | X239: Express | Y239: 42.15 | Z239: 7 | AA239: =IF(Table2[[#This Row],[DeliveryDays]]<=3,"FAST DELIVERY","LATE DELIVERY") -> LATE DELIVERY | AB239: Corporate | AC239: Yes | AD239: 3 | AE239: =_xlfn.IFS(Table2[[#This Row],[Rating]]=5,"Excellent",Table2[[#This Row],[Rating]]=4,"Good",Table2[[#This Row],[Rating]]=3,"Average",Table2[[#This Row],[Rating]]<=2,"Poor") -> Average | AF239: =Table2[[#This Row],[Cost]]+Table2[[#This Row],[Profit]]+Table2[[#This Row],[ShippingCost]]+Table2[[#This Row],[DeliveryDays]] -> 10519.22 | AG239: =Table2[[#This Row],[Profit]]/Table2[[#This Row],[Cost]] -> 0.18365794 | AQ239: Show only orders from India.
A240: 239 | B240: 2023-12-24 | C240: =YEAR(Table2[[#This Row],[Date]]) -> 2023 | D240: =TEXT(Table2[[#This Row],[Date]],"mmmm") -> December | E240: David | F240: West | G240: Germany | H240: Berlin | I240: Office Supplies | J240: Laptop | K240: Distributor | L240: Rep B | M240: 288.3 | N240: 20 | O240: 0.25 | P240: =IF(Table2[[#This Row],[Discount]]>20%,"HIGH","LOW") -> HIGH | Q240: 4324.5 | R240: =_xlfn.IFS(Table2[[#This Row],[Revenue]]<1000,"Small",OR(Table2[[#This Row],[Revenue]]>1000,Table2[[#This Row],[Revenue]]<=5000),"Medium",Table2[[#This Row],[Revenue]]>5000,"Large") -> Medium | S240: =IF(Table2[[#This Row],[Revenue]]>3000,"Premium","Not Premium") -> Premium | T240: 2356.69 | U240: 1967.81 | V240: Credit Card | W240: Low | X240: Express | Y240: 38.97 | Z240: 1 | AA240: =IF(Table2[[#This Row],[DeliveryDays]]<=3,"FAST DELIVERY","LATE DELIVERY") -> FAST DELIVERY | AB240: Consumer | AC240: Yes | AD240: 4 | AE240: =_xlfn.IFS(Table2[[#This Row],[Rating]]=5,"Excellent",Table2[[#This Row],[Rating]]=4,"Good",Table2[[#This Row],[Rating]]=3,"Average",Table2[[#This Row],[Rating]]<=2,"Poor") -> Good | AF240: =Table2[[#This Row],[Cost]]+Table2[[#This Row],[Profit]]+Table2[[#This Row],[ShippingCost]]+Table2[[#This Row],[DeliveryDays]] -> 4364.47 | AG240: =Table2[[#This Row],[Profit]]/Table2[[#This Row],[Cost]] -> 0.8349889 | AQ240: Country
A241: 240 | B241: 2024-01-26 | C241: =YEAR(Table2[[#This Row],[Date]]) -> 2024 | D241: =TEXT(Table2[[#This Row],[Date]],"mmmm") -> January | E241: Arjun | F241: South | G241: UK | H241: Sydney | I241: Office Supplies | J241: T-Shirt | K241: Retail | L241: Rep C | M241: 947.75 | N241: 20 | O241: 0.07 | P241: =IF(Table2[[#This Row],[Discount]]>20%,"HIGH","LOW") -> LOW | Q241: 17628.15 | R241: =_xlfn.IFS(Table2[[#This Row],[Revenue]]<1000,"Small",OR(Table2[[#This Row],[Revenue]]>1000,Table2[[#This Row],[Revenue]]<=5000),"Medium",Table2[[#This Row],[Revenue]]>5000,"Large") -> Medium | S241: =IF(Table2[[#This Row],[Revenue]]>3000,"Premium","Not Premium") -> Premium | T241: 14573.41 | U241: 3054.74 | V241: Cash | W241: Low | X241: Standard | Y241: 18.06 | Z241: 4 | AA241: =IF(Table2[[#This Row],[DeliveryDays]]<=3,"FAST DELIVERY","LATE DELIVERY") -> LATE DELIVERY | AB241: Consumer | AC241: Yes | AD241: 1 | AE241: =_xlfn.IFS(Table2[[#This Row],[Rating]]=5,"Excellent",Table2[[#This Row],[Rating]]=4,"Good",Table2[[#This Row],[Rating]]=3,"Average",Table2[[#This Row],[Rating]]<=2,"Poor") -> Poor | AF241: =Table2[[#This Row],[Cost]]+Table2[[#This Row],[Profit]]+Table2[[#This Row],[ShippingCost]]+Table2[[#This Row],[DeliveryDays]] -> 17650.21 | AG241: =Table2[[#This Row],[Profit]]/Table2[[#This Row],[Cost]] -> 0.20961052 | AQ241: India
A242: 241 | B242: 2023-04-14 | C242: =YEAR(Table2[[#This Row],[Date]]) -> 2023 | D242: =TEXT(Table2[[#This Row],[Date]],"mmmm") -> April | E242: Priya | F242: North | G242: India | H242: Sydney | I242: Sports | J242: Printer | K242: Distributor | L242: Rep A | M242: 416.66 | N242: 14 | O242: 0.19 | P242: =IF(Table2[[#This Row],[Discount]]>20%,"HIGH","LOW") -> LOW | Q242: 4724.92 | R242: =_xlfn.IFS(Table2[[#This Row],[Revenue]]<1000,"Small",OR(Table2[[#This Row],[Revenue]]>1000,Table2[[#This Row],[Revenue]]<=5000),"Medium",Table2[[#This Row],[Revenue]]>5000,"Large") -> Medium | S242: =IF(Table2[[#This Row],[Revenue]]>3000,"Premium","Not Premium") -> Premium | T242: 3422.1 | U242: 1302.82 | V242: PayPal | W242: High | X242: Standard | Y242: 11.97 | Z242: 4 | AA242: =IF(Table2[[#This Row],[DeliveryDays]]<=3,"FAST DELIVERY","LATE DELIVERY") -> LATE DELIVERY | AB242: Corporate | AC242: No | AD242: 5 | AE242: =_xlfn.IFS(Table2[[#This Row],[Rating]]=5,"Excellent",Table2[[#This Row],[Rating]]=4,"Good",Table2[[#This Row],[Rating]]=3,"Average",Table2[[#This Row],[Rating]]<=2,"Poor") -> Excellent | AF242: =Table2[[#This Row],[Cost]]+Table2[[#This Row],[Profit]]+Table2[[#This Row],[ShippingCost]]+Table2[[#This Row],[DeliveryDays]] -> 4740.89 | AG242: =Table2[[#This Row],[Profit]]/Table2[[#This Row],[Cost]] -> 0.38070775 | BO242: Month
A243: 242 | B243: 2024-09-14 | C243: =YEAR(Table2[[#This Row],[Date]]) -> 2024 | D243: =TEXT(Table2[[#This Row],[Date]],"mmmm") -> September | E243: Neha | F243: North | G243: Australia | H243: Pune | I243: Electronics | J243: Jacket | K243: Distributor | L243: Rep D | M243: 698.88 | N243: 11 | O243: 0.1 | P243: =IF(Table2[[#This Row],[Discount]]>20%,"HIGH","LOW") -> LOW | Q243: 6918.91 | R243: =_xlfn.IFS(Table2[[#This Row],[Revenue]]<1000,"Small",OR(Table2[[#This Row],[Revenue]]>1000,Table2[[#This Row],[Revenue]]<=5000),"Medium",Table2[[#This Row],[Revenue]]>5000,"Large") -> Medium | S243: =IF(Table2[[#This Row],[Revenue]]>3000,"Premium","Not Premium") -> Premium | T243: 4239.7 | U243: 2679.21 | V243: UPI | W243: Critical | X243: Standard | Y243: 37.4 | Z243: 4 | AA243: =IF(Table2[[#This Row],[DeliveryDays]]<=3,"FAST DELIVERY","LATE DELIVERY") -> LATE DELIVERY | AB243: Home Office | AC243: No | AD243: 3 | AE243: =_xlfn.IFS(Table2[[#This Row],[Rating]]=5,"Excellent",Table2[[#This Row],[Rating]]=4,"Good",Table2[[#This Row],[Rating]]=3,"Average",Table2[[#This Row],[Rating]]<=2,"Poor") -> Average | AF243: =Table2[[#This Row],[Cost]]+Table2[[#This Row],[Profit]]+Table2[[#This Row],[ShippingCost]]+Table2[[#This Row],[DeliveryDays]] -> 6960.31 | AG243: =Table2[[#This Row],[Profit]]/Table2[[#This Row],[Cost]] -> 0.63193386 | AQ243: OrderID | AR243: Date | AS243: CustomerName | AT243: Region | AU243: Country | AV243: City | AW243: ProductCategory | AX243: ProductName | AY243: SalesChannel | AZ243: SalesRep | BA243: UnitPrice | BB243: Quantity | BC243: Discount | BD243: Revenue | BE243: Cost | BF243: Profit | BG243: PaymentMethod | BH243: OrderPriority | BI243: ShipMode | BJ243: ShippingCost | BK243: DeliveryDays | BL243: CustomerSegment | BM243: Returned | BN243: Rating | BO243: 1
A244: 243 | B244: 2023-03-17 | C244: =YEAR(Table2[[#This Row],[Date]]) -> 2023 | D244: =TEXT(Table2[[#This Row],[Date]],"mmmm") -> March | E244: David | F244: East | G244: USA | H244: Mumbai | I244: Clothing | J244: Monitor | K244: Online | L244: Rep B | M244: 99.85 | N244: 2 | O244: 0.23 | P244: =IF(Table2[[#This Row],[Discount]]>20%,"HIGH","LOW") -> HIGH | Q244: 153.77 | R244: =_xlfn.IFS(Table2[[#This Row],[Revenue]]<1000,"Small",OR(Table2[[#This Row],[Revenue]]>1000,Table2[[#This Row],[Revenue]]<=5000),"Medium",Table2[[#This Row],[Revenue]]>5000,"Large") -> Small | S244: =IF(Table2[[#This Row],[Revenue]]>3000,"Premium","Not Premium") -> Not Premium | T244: 121.37 | U244: 32.4 | V244: Cash | W244: High | X244: Express | Y244: 47.68 | Z244: 7 | AA244: =IF(Table2[[#This Row],[DeliveryDays]]<=3,"FAST DELIVERY","LATE DELIVERY") -> LATE DELIVERY | AB244: Consumer | AC244: Yes | AD244: 5 | AE244: =_xlfn.IFS(Table2[[#This Row],[Rating]]=5,"Excellent",Table2[[#This Row],[Rating]]=4,"Good",Table2[[#This Row],[Rating]]=3,"Average",Table2[[#This Row],[Rating]]<=2,"Poor") -> Excellent | AF244: =Table2[[#This Row],[Cost]]+Table2[[#This Row],[Profit]]+Table2[[#This Row],[ShippingCost]]+Table2[[#This Row],[DeliveryDays]] -> 208.45 | AG244: =Table2[[#This Row],[Profit]]/Table2[[#This Row],[Cost]] -> 0.26695229 | AQ244: 4 | AR244: 2023-01-07 | AS244: Riya | AT244: South | AU244: India | AV244: Sydney | AW244: Furniture | AX244: Chair | AY244: Retail | AZ244: Rep D | BA244: 438.12 | BB244: 16 | BC244: 0.28 | BD244: 5047.14 | BE244: 2684.67 | BF244: 2362.47 | BG244: PayPal | BH244: Critical | BI244: Same Day | BJ244: 23.41 | BK244: 3 | BL244: Home Office | BM244: Yes | BN244: 1 | BO244: 5
A245: 244 | B245: 2023-03-21 | C245: =YEAR(Table2[[#This Row],[Date]]) -> 2023 | D245: =TEXT(Table2[[#This Row],[Date]],"mmmm") -> March | E245: Rahul | F245: South | G245: UK | H245: Delhi | I245: Sports | J245: Chair | K245: Retail | L245: Rep D | M245: 77.23 | N245: 14 | O245: 0.22 | P245: =IF(Table2[[#This Row],[Discount]]>20%,"HIGH","LOW") -> HIGH | Q245: 843.35 | R245: =_xlfn.IFS(Table2[[#This Row],[Revenue]]<1000,"Small",OR(Table2[[#This Row],[Revenue]]>1000,Table2[[#This Row],[Revenue]]<=5000),"Medium",Table2[[#This Row],[Revenue]]>5000,"Large") -> Small | S245: =IF(Table2[[#This Row],[Revenue]]>3000,"Premium","Not Premium") -> Not Premium | T245: 488.82 | U245: 354.53 | V245: Credit Card | W245: Medium | X245: Express | Y245: 5.77 | Z245: 1 | AA245: =IF(Table2[[#This Row],[DeliveryDays]]<=3,"FAST DELIVERY","LATE DELIVERY") -> FAST DELIVERY | AB245: Consumer | AC245: No | AD245: 5 | AE245: =_xlfn.IFS(Table2[[#This Row],[Rating]]=5,"Excellent",Table2[[#This Row],[Rating]]=4,"Good",Table2[[#This Row],[Rating]]=3,"Average",Table2[[#This Row],[Rating]]<=2,"Poor") -> Excellent | AF245: =Table2[[#This Row],[Cost]]+Table2[[#This Row],[Profit]]+Table2[[#This Row],[ShippingCost]]+Table2[[#This Row],[DeliveryDays]] -> 850.12 | AG245: =Table2[[#This Row],[Profit]]/Table2[[#This Row],[Cost]] -> 0.7252772 | AQ245: 5 | AR245: 2024-05-25 | AS245: Sophia | AT245: East | AU245: India | AV245: Pune | AW245: Office Supplies | AX245: Desk | AY245: Retail | AZ245: Rep A | BA245: 80.22 | BB245: 15 | BC245: 0 | BD245: 1203.3 | BE245: 745.46 | BF245: 457.84 | BG245: Bank Transfer | BH245: Low | BI245: Express | BJ245: 29.52 | BK245: 8 | BL245: Home Office | BM245: Yes | BN245: 1 | BO245: 5
A246: 245 | B246: 2024-02-18 | C246: =YEAR(Table2[[#This Row],[Date]]) -> 2024 | D246: =TEXT(Table2[[#This Row],[Date]],"mmmm") -> February | E246: Riya | F246: East | G246: UK | H246: New York | I246: Furniture | J246: Tablet | K246: Online | L246: Rep B | M246: 341.25 | N246: 6 | O246: 0.19 | P246: =IF(Table2[[#This Row],[Discount]]>20%,"HIGH","LOW") -> LOW | Q246: 1658.48 | R246: =_xlfn.IFS(Table2[[#This Row],[Revenue]]<1000,"Small",OR(Table2[[#This Row],[Revenue]]>1000,Table2[[#This Row],[Revenue]]<=5000),"Medium",Table2[[#This Row],[Revenue]]>5000,"Large") -> Medium | S246: =IF(Table2[[#This Row],[Revenue]]>3000,"Premium","Not Premium") -> Not Premium | T246: 976.94 | U246: 681.54 | V246: Bank Transfer | W246: Low | X246: Same Day | Y246: 29.56 | Z246: 8 | AA246: =IF(Table2[[#This Row],[DeliveryDays]]<=3,"FAST DELIVERY","LATE DELIVERY") -> LATE DELIVERY | AB246: Corporate | AC246: No | AD246: 4 | AE246: =_xlfn.IFS(Table2[[#This Row],[Rating]]=5,"Excellent",Table2[[#This Row],[Rating]]=4,"Good",Table2[[#This Row],[Rating]]=3,"Average",Table2[[#This Row],[Rating]]<=2,"Poor") -> Good | AF246: =Table2[[#This Row],[Cost]]+Table2[[#This Row],[Profit]]+Table2[[#This Row],[ShippingCost]]+Table2[[#This Row],[DeliveryDays]] -> 1696.04 | AG246: =Table2[[#This Row],[Profit]]/Table2[[#This Row],[Cost]] -> 0.69762729 | AQ246: 6 | AR246: 2023-05-07 | AS246: Riya | AT246: East | AU246: India | AV246: Delhi | AW246: Clothing | AX246: Jacket | AY246: Distributor | AZ246: Rep A | BA246: 956.16 | BB246: 2 | BC246: 0 | BD246: 1912.32 | BE246: 1376.98 | BF246: 535.34 | BG246: Cash | BH246: Low | BI246: Express | BJ246: 7.77 | BK246: 2 | BL246: Corporate | BM246: Yes | BN246: 4 | BO246: 6
A247: 246 | B247: 2023-12-14 | C247: =YEAR(Table2[[#This Row],[Date]]) -> 2023 | D247: =TEXT(Table2[[#This Row],[Date]],"mmmm") -> December | E247: Amit | F247: South | G247: Canada | H247: Mumbai | I247: Electronics | J247: T-Shirt | K247: Distributor | L247: Rep D | M247: 175.54 | N247: 12 | O247: 0.27 | P247: =IF(Table2[[#This Row],[Discount]]>20%,"HIGH","LOW") -> HIGH | Q247: 1537.73 | R247: =_xlfn.IFS(Table2[[#This Row],[Revenue]]<1000,"Small",OR(Table2[[#This Row],[Revenue]]>1000,Table2[[#This Row],[Revenue]]<=5000),"Medium",Table2[[#This Row],[Revenue]]>5000,"Large") -> Medium | S247: =IF(Table2[[#This Row],[Revenue]]>3000,"Premium","Not Premium") -> Not Premium | T247: 854.29 | U247: 683.44 | V247: PayPal | W247: Low | X247: Standard | Y247: 42.86 | Z247: 7 | AA247: =IF(Table2[[#This Row],[DeliveryDays]]<=3,"FAST DELIVERY","LATE DELIVERY") -> LATE DELIVERY | AB247: Corporate | AC247: Yes | AD247: 1 | AE247: =_xlfn.IFS(Table2[[#This Row],[Rating]]=5,"Excellent",Table2[[#This Row],[Rating]]=4,"Good",Table2[[#This Row],[Rating]]=3,"Average",Table2[[#This Row],[Rating]]<=2,"Poor") -> Poor | AF247: =Table2[[#This Row],[Cost]]+Table2[[#This Row],[Profit]]+Table2[[#This Row],[ShippingCost]]+Table2[[#This Row],[DeliveryDays]] -> 1587.59 | AG247: =Table2[[#This Row],[Profit]]/Table2[[#This Row],[Cost]] -> 0.80000936 | AQ247: 7 | AR247: 2024-06-19 | AS247: David | AT247: East | AU247: India | AV247: New York | AW247: Office Supplies | AX247: Tablet | AY247: Retail | AZ247: Rep B | BA247: 342.02 | BB247: 20 | BC247: 0.08 | BD247: 6293.17 | BE247: 3483.81 | BF247: 2809.36 | BG247: Cash | BH247: Low | BI247: Standard | BJ247: 32.24 | BK247: 2 | BL247: Home Office | BM247: Yes | BN247: 3 | BO247: 4
A248: 247 | B248: 2024-07-23 | C248: =YEAR(Table2[[#This Row],[Date]]) -> 2024 | D248: =TEXT(Table2[[#This Row],[Date]],"mmmm") -> July | E248: Anita | F248: North | G248: Canada | H248: Delhi | I248: Office Supplies | J248: Laptop | K248: Retail | L248: Rep D | M248: 473.6 | N248: 10 | O248: 0.07 | P248: =IF(Table2[[#This Row],[Discount]]>20%,"HIGH","LOW") -> LOW | Q248: 4404.48 | R248: =_xlfn.IFS(Table2[[#This Row],[Revenue]]<1000,"Small",OR(Table2[[#This Row],[Revenue]]>1000,Table2[[#This Row],[Revenue]]<=5000),"Medium",Table2[[#This Row],[Revenue]]>5000,"Large") -> Medium | S248: =IF(Table2[[#This Row],[Revenue]]>3000,"Premium","Not Premium") -> Premium | T248: 3517.21 | U248: 887.27 | V248: Bank Transfer | W248: Medium | X248: Express | Y248: 25.72 | Z248: 1 | AA248: =IF(Table2[[#This Row],[DeliveryDays]]<=3,"FAST DELIVERY","LATE DELIVERY") -> FAST DELIVERY | AB248: Consumer | AC248: No | AD248: 2 | AE248: =_xlfn.IFS(Table2[[#This Row],[Rating]]=5,"Excellent",Table2[[#This Row],[Rating]]=4,"Good",Table2[[#This Row],[Rating]]=3,"Average",Table2[[#This Row],[Rating]]<=2,"Poor") -> Poor | AF248: =Table2[[#This Row],[Cost]]+Table2[[#This Row],[Profit]]+Table2[[#This Row],[ShippingCost]]+Table2[[#This Row],[DeliveryDays]] -> 4431.2 | AG248: =Table2[[#This Row],[Profit]]/Table2[[#This Row],[Cost]] -> 0.25226529 | AQ248: 27 | AR248: 2023-04-27 | AS248: Arjun | AT248: North | AU248: India | AV248: New York | AW248: Electronics | AX248: Football | AY248: Online | AZ248: Rep E | BA248: 600.43 | BB248: 17 | BC248: 0.17 | BD248: 8472.07 | BE248: 4854.92 | BF248: 3617.15 | BG248: Credit Card | BH248: Low | BI248: Same Day | BJ248: 12.96 | BK248: 6 | BL248: Home Office | BM248: Yes | BN248: 5 | BO248: 5
A249: 248 | B249: 2023-08-13 | C249: =YEAR(Table2[[#This Row],[Date]]) -> 2023 | D249: =TEXT(Table2[[#This Row],[Date]],"mmmm") -> August | E249: Rahul | F249: East | G249: India | H249: Mumbai | I249: Furniture | J249: Football | K249: Distributor | L249: Rep E | M249: 355.28 | N249: 3 | O249: 0.25 | P249: =IF(Table2[[#This Row],[Discount]]>20%,"HIGH","LOW") -> HIGH | Q249: 799.38 | R249: =_xlfn.IFS(Table2[[#This Row],[Revenue]]<1000,"Small",OR(Table2[[#This Row],[Revenue]]>1000,Table2[[#This Row],[Revenue]]<=5000),"Medium",Table2[[#This Row],[Revenue]]>5000,"Large") -> Small | S249: =IF(Table2[[#This Row],[Revenue]]>3000,"Premium","Not Premium") -> Not Premium | T249: 607.36 | U249: 192.02 | V249: Bank Transfer | W249: Medium | X249: Same Day | Y249: 23.95 | Z249: 3 | AA249: =IF(Table2[[#This Row],[DeliveryDays]]<=3,"FAST DELIVERY","LATE DELIVERY") -> FAST DELIVERY | AB249: Consumer | AC249: Yes | AD249: 5 | AE249: =_xlfn.IFS(Table2[[#This Row],[Rating]]=5,"Excellent",Table2[[#This Row],[Rating]]=4,"Good",Table2[[#This Row],[Rating]]=3,"Average",Table2[[#This Row],[Rating]]<=2,"Poor") -> Excellent | AF249: =Table2[[#This Row],[Cost]]+Table2[[#This Row],[Profit]]+Table2[[#This Row],[ShippingCost]]+Table2[[#This Row],[DeliveryDays]] -> 826.33 | AG249: =Table2[[#This Row],[Profit]]/Table2[[#This Row],[Cost]] -> 0.31615516 | AQ249: 28 | AR249: 2023-05-19 | AS249: Amit | AT249: North | AU249: India | AV249: Toronto | AW249: Electronics | AX249: T-Shirt | AY249: Retail | AZ249: Rep D | BA249: 697.99 | BB249: 7 | BC249: 0.1 | BD249: 4397.34 | BE249: 2823.58 | BF249: 1573.76 | BG249: UPI | BH249: Critical | BI249: Same Day | BJ249: 27.37 | BK249: 1 | BL249: Consumer | BM249: Yes | BN249: 5 | BO249: 4
A250: 249 | B250: 2024-08-08 | C250: =YEAR(Table2[[#This Row],[Date]]) -> 2024 | D250: =TEXT(Table2[[#This Row],[Date]],"mmmm") -> August | E250: Neha | F250: West | G250: India | H250: Berlin | I250: Furniture | J250: T-Shirt | K250: Online | L250: Rep C | M250: 575.63 | N250: 16 | O250: 0 | P250: =IF(Table2[[#This Row],[Discount]]>20%,"HIGH","LOW") -> LOW | Q250: 9210.08 | R250: =_xlfn.IFS(Table2[[#This Row],[Revenue]]<1000,"Small",OR(Table2[[#This Row],[Revenue]]>1000,Table2[[#This Row],[Revenue]]<=5000),"Medium",Table2[[#This Row],[Revenue]]>5000,"Large") -> Medium | S250: =IF(Table2[[#This Row],[Revenue]]>3000,"Premium","Not Premium") -> Premium | T250: 7741.91 | U250: 1468.17 | V250: Credit Card | W250: Critical | X250: Standard | Y250: 11.19 | Z250: 4 | AA250: =IF(Table2[[#This Row],[DeliveryDays]]<=3,"FAST DELIVERY","LATE DELIVERY") -> LATE DELIVERY | AB250: Corporate | AC250: Yes | AD250: 1 | AE250: =_xlfn.IFS(Table2[[#This Row],[Rating]]=5,"Excellent",Table2[[#This Row],[Rating]]=4,"Good",Table2[[#This Row],[Rating]]=3,"Average",Table2[[#This Row],[Rating]]<=2,"Poor") -> Poor | AF250: =Table2[[#This Row],[Cost]]+Table2[[#This Row],[Profit]]+Table2[[#This Row],[ShippingCost]]+Table2[[#This Row],[DeliveryDays]] -> 9225.27 | AG250: =Table2[[#This Row],[Profit]]/Table2[[#This Row],[Cost]] -> 0.18963925 | AQ250: 30 | AR250: 2023-04-09 | AS250: Anita | AT250: East | AU250: India | AV250: Mumbai | AW250: Furniture | AX250: T-Shirt | AY250: Online | AZ250: Rep E | BA250: 471.7 | BB250: 14 | BC250: 0.27 | BD250: 4820.77 | BE250: 3546.14 | BF250: 1274.63 | BG250: Bank Transfer | BH250: Medium | BI250: Express | BJ250: 29.81 | BK250: 2 | BL250: Consumer | BM250: No | BN250: 5 | BO250: 3
A251: 250 | B251: 2024-03-20 | C251: =YEAR(Table2[[#This Row],[Date]]) -> 2024 | D251: =TEXT(Table2[[#This Row],[Date]],"mmmm") -> March | E251: Sara | F251: East | G251: UK | H251: Berlin | I251: Office Supplies | J251: Jacket | K251: Online | L251: Rep C | M251: 221.98 | N251: 11 | O251: 0.08 | P251: =IF(Table2[[#This Row],[Discount]]>20%,"HIGH","LOW") -> LOW | Q251: 2246.44 | R251: =_xlfn.IFS(Table2[[#This Row],[Revenue]]<1000,"Small",OR(Table2[[#This Row],[Revenue]]>1000,Table2[[#This Row],[Revenue]]<=5000),"Medium",Table2[[#This Row],[Revenue]]>5000,"Large") -> Medium | S251: =IF(Table2[[#This Row],[Revenue]]>3000,"Premium","Not Premium") -> Not Premium | T251: 2013.81 | U251: 232.63 | V251: Credit Card | W251: Low | X251: Express | Y251: 10.42 | Z251: 7 | AA251: =IF(Table2[[#This Row],[DeliveryDays]]<=3,"FAST DELIVERY","LATE DELIVERY") -> LATE DELIVERY | AB251: Consumer | AC251: Yes | AD251: 1 | AE251: =_xlfn.IFS(Table2[[#This Row],[Rating]]=5,"Excellent",Table2[[#This Row],[Rating]]=4,"Good",Table2[[#This Row],[Rating]]=3,"Average",Table2[[#This Row],[Rating]]<=2,"Poor") -> Poor | AF251: =Table2[[#This Row],[Cost]]+Table2[[#This Row],[Profit]]+Table2[[#This Row],[ShippingCost]]+Table2[[#This Row],[DeliveryDays]] -> 2263.86 | AG251: =Table2[[#This Row],[Profit]]/Table2[[#This Row],[Cost]] -> 0.11551735 | AQ251: 33 | AR251: 2024-03-16 | AS251: Arjun | AT251: West | AU251: India | AV251: New York | AW251: Furniture | AX251: Jacket | AY251: Distributor | AZ251: Rep D | BA251: 103.94 | BB251: 4 | BC251: 0.15 | BD251: 353.4 | BE251: 206.51 | BF251: 146.89 | BG251: Credit Card | BH251: Low | BI251: Same Day | BJ251: 29.93 | BK251: 3 | BL251: Corporate | BM251: Yes | BN251: 5 | BO251: 10
A252: 251 | B252: 2024-02-18 | C252: =YEAR(Table2[[#This Row],[Date]]) -> 2024 | D252: =TEXT(Table2[[#This Row],[Date]],"mmmm") -> February | E252: Riya | F252: North | G252: India | H252: Pune | I252: Electronics | J252: Desk | K252: Distributor | L252: Rep E | M252: 826.99 | N252: 5 | O252: 0.14 | P252: =IF(Table2[[#This Row],[Discount]]>20%,"HIGH","LOW") -> LOW | Q252: 3556.06 | R252: =_xlfn.IFS(Table2[[#This Row],[Revenue]]<1000,"Small",OR(Table2[[#This Row],[Revenue]]>1000,Table2[[#This Row],[Revenue]]<=5000),"Medium",Table2[[#This Row],[Revenue]]>5000,"Large") -> Medium | S252: =IF(Table2[[#This Row],[Revenue]]>3000,"Premium","Not Premium") -> Premium | T252: 1925.75 | U252: 1630.31 | V252: Bank Transfer | W252: High | X252: Express | Y252: 41.39 | Z252: 9 | AA252: =IF(Table2[[#This Row],[DeliveryDays]]<=3,"FAST DELIVERY","LATE DELIVERY") -> LATE DELIVERY | AB252: Consumer | AC252: No | AD252: 2 | AE252: =_xlfn.IFS(Table2[[#This Row],[Rating]]=5,"Excellent",Table2[[#This Row],[Rating]]=4,"Good",Table2[[#This Row],[Rating]]=3,"Average",Table2[[#This Row],[Rating]]<=2,"Poor") -> Poor | AF252: =Table2[[#This Row],[Cost]]+Table2[[#This Row],[Profit]]+Table2[[#This Row],[ShippingCost]]+Table2[[#This Row],[DeliveryDays]] -> 3606.45 | AG252: =Table2[[#This Row],[Profit]]/Table2[[#This Row],[Cost]] -> 0.84658445 | AQ252: 38 | AR252: 2024-10-31 | AS252: Riya | AT252: South | AU252: India | AV252: Toronto | AW252: Clothing | AX252: T-Shirt | AY252: Online | AZ252: Rep D | BA252: 804.65 | BB252: 5 | BC252: 0.13 | BD252: 3500.23 | BE252: 2149.83 | BF252: 1350.4 | BG252: PayPal | BH252: Low | BI252: Express | BJ252: 11.72 | BK252: 1 | BL252: Home Office | BM252: Yes | BN252: 2 | BO252: 6
A253: 252 | B253: 2024-12-06 | C253: =YEAR(Table2[[#This Row],[Date]]) -> 2024 | D253: =TEXT(Table2[[#This Row],[Date]],"mmmm") -> December | E253: Rahul | F253: South | G253: Canada | H253: Berlin | I253: Electronics | J253: Laptop | K253: Online | L253: Rep E | M253: 345.15 | N253: 19 | O253: 0.22 | P253: =IF(Table2[[#This Row],[Discount]]>20%,"HIGH","LOW") -> HIGH | Q253: 5115.12 | R253: =_xlfn.IFS(Table2[[#This Row],[Revenue]]<1000,"Small",OR(Table2[[#This Row],[Revenue]]>1000,Table2[[#This Row],[Revenue]]<=5000),"Medium",Table2[[#This Row],[Revenue]]>5000,"Large") -> Medium | S253: =IF(Table2[[#This Row],[Revenue]]>3000,"Premium","Not Premium") -> Premium | T253: 3453.11 | U253: 1662.01 | V253: Credit Card | W253: Critical | X253: Standard | Y253: 11.58 | Z253: 2 | AA253: =IF(Table2[[#This Row],[DeliveryDays]]<=3,"FAST DELIVERY","LATE DELIVERY") -> FAST DELIVERY | AB253: Home Office | AC253: Yes | AD253: 2 | AE253: =_xlfn.IFS(Table2[[#This Row],[Rating]]=5,"Excellent",Table2[[#This Row],[Rating]]=4,"Good",Table2[[#This Row],[Rating]]=3,"Average",Table2[[#This Row],[Rating]]<=2,"Poor") -> Poor | AF253: =Table2[[#This Row],[Cost]]+Table2[[#This Row],[Profit]]+Table2[[#This Row],[ShippingCost]]+Table2[[#This Row],[DeliveryDays]] -> 5128.7 | AG253: =Table2[[#This Row],[Profit]]/Table2[[#This Row],[Cost]] -> 0.48130815 | AQ253: 46 | AR253: 2023-06-17 | AS253: Michael | AT253: North | AU253: India | AV253: Mumbai | AW253: Furniture | AX253: Printer | AY253: Distributor | AZ253: Rep D | BA253: 256.77 | BB253: 16 | BC253: 0.23 | BD253: 3163.41 | BE253: 1847.04 | BF253: 1316.37 | BG253: UPI | BH253: High | BI253: Standard | BJ253: 49.27 | BK253: 10 | BL253: Consumer | BM253: Yes | BN253: 2 | BO253: 7
A254: 253 | B254: 2024-03-28 | C254: =YEAR(Table2[[#This Row],[Date]]) -> 2024 | D254: =TEXT(Table2[[#This Row],[Date]],"mmmm") -> March | E254: Sara | F254: East | G254: Australia | H254: Mumbai | I254: Sports | J254: Tablet | K254: Online | L254: Rep B | M254: 258.85 | N254: 16 | O254: 0.02 | P254: =IF(Table2[[#This Row],[Discount]]>20%,"HIGH","LOW") -> LOW | Q254: 4058.77 | R254: =_xlfn.IFS(Table2[[#This Row],[Revenue]]<1000,"Small",OR(Table2[[#This Row],[Revenue]]>1000,Table2[[#This Row],[Revenue]]<=5000),"Medium",Table2[[#This Row],[Revenue]]>5000,"Large") -> Medium | S254: =IF(Table2[[#This Row],[Revenue]]>3000,"Premium","Not Premium") -> Premium | T254: 2049.7 | U254: 2009.07 | V254: Bank Transfer | W254: Low | X254: Same Day | Y254: 28.14 | Z254: 9 | AA254: =IF(Table2[[#This Row],[DeliveryDays]]<=3,"FAST DELIVERY","LATE DELIVERY") -> LATE DELIVERY | AB254: Corporate | AC254: No | AD254: 1 | AE254: =_xlfn.IFS(Table2[[#This Row],[Rating]]=5,"Excellent",Table2[[#This Row],[Rating]]=4,"Good",Table2[[#This Row],[Rating]]=3,"Average",Table2[[#This Row],[Rating]]<=2,"Poor") -> Poor | AF254: =Table2[[#This Row],[Cost]]+Table2[[#This Row],[Profit]]+Table2[[#This Row],[ShippingCost]]+Table2[[#This Row],[DeliveryDays]] -> 4095.91 | AG254: =Table2[[#This Row],[Profit]]/Table2[[#This Row],[Cost]] -> 0.98017759 | AQ254: 48 | AR254: 2024-07-05 | AS254: Rahul | AT254: West | AU254: India | AV254: Toronto | AW254: Furniture | AX254: Keyboard | AY254: Retail | AZ254: Rep D | BA254: 398.28 | BB254: 19 | BC254: 0.08 | BD254: 6961.93 | BE254: 4606.63 | BF254: 2355.3 | BG254: Credit Card | BH254: Low | BI254: Standard | BJ254: 29.83 | BK254: 2 | BL254: Consumer | BM254: No | BN254: 3 | BO254: 3
A255: 254 | B255: 2024-07-27 | C255: =YEAR(Table2[[#This Row],[Date]]) -> 2024 | D255: =TEXT(Table2[[#This Row],[Date]],"mmmm") -> July | E255: Michael | F255: South | G255: Australia | H255: Sydney | I255: Electronics | J255: Chair | K255: Online | L255: Rep A | M255: 131.55 | N255: 18 | O255: 0.19 | P255: =IF(Table2[[#This Row],[Discount]]>20%,"HIGH","LOW") -> LOW | Q255: 1918 | R255: =_xlfn.IFS(Table2[[#This Row],[Revenue]]<1000,"Small",OR(Table2[[#This Row],[Revenue]]>1000,Table2[[#This Row],[Revenue]]<=5000),"Medium",Table2[[#This Row],[Revenue]]>5000,"Large") -> Medium | S255: =IF(Table2[[#This Row],[Revenue]]>3000,"Premium","Not Premium") -> Not Premium | T255: 1523.69 | U255: 394.31 | V255: Bank Transfer | W255: Medium | X255: Express | Y255: 20.94 | Z255: 8 | AA255: =IF(Table2[[#This Row],[DeliveryDays]]<=3,"FAST DELIVERY","LATE DELIVERY") -> LATE DELIVERY | AB255: Consumer | AC255: No | AD255: 2 | AE255: =_xlfn.IFS(Table2[[#This Row],[Rating]]=5,"Excellent",Table2[[#This Row],[Rating]]=4,"Good",Table2[[#This Row],[Rating]]=3,"Average",Table2[[#This Row],[Rating]]<=2,"Poor") -> Poor | AF255: =Table2[[#This Row],[Cost]]+Table2[[#This Row],[Profit]]+Table2[[#This Row],[ShippingCost]]+Table2[[#This Row],[DeliveryDays]] -> 1946.94 | AG255: =Table2[[#This Row],[Profit]]/Table2[[#This Row],[Cost]] -> 0.25878624 | AQ255: 54 | AR255: 2024-03-17 | AS255: Rahul | AT255: South | AU255: India | AV255: Pune | AW255: Electronics | AX255: Football | AY255: Online | AZ255: Rep A | BA255: 288.68 | BB255: 2 | BC255: 0.02 | BD255: 565.81 | BE255: 451.49 | BF255: 114.32 | BG255: Bank Transfer | BH255: High | BI255: Standard | BJ255: 36.45 | BK255: 7 | BL255: Home Office | BM255: Yes | BN255: 5 | BO255: 2
... A426: 425 | B426: 2023-05-17 | C426: =YEAR(Table2[[#This Row],[Date]]) -> 2023 | D426: =TEXT(Table2[[#This Row],[Date]],"mmmm") -> May | E426: Priya | F426: South | G426: India | H426: Toronto | I426: Office Supplies | J426: Desk | K426: Distributor | L426: Rep A | M426: 774.55 | N426: 9 | O426: 0.08 | P426: =IF(Table2[[#This Row],[Discount]]>20%,"HIGH","LOW") -> LOW | Q426: 6413.27 | R426: =_xlfn.IFS(Table2[[#This Row],[Revenue]]<1000,"Small",OR(Table2[[#This Row],[Revenue]]>1000,Table2[[#This Row],[Revenue]]<=5000),"Medium",Table2[[#This Row],[Revenue]]>5000,"Large") -> Medium | S426: =IF(Table2[[#This Row],[Revenue]]>3000,"Premium","Not Premium") -> Premium | T426: 3802.68 | U426: 2610.59 | V426: Credit Card | W426: Low | X426: Standard | Y426: 23.45 | Z426: 8 | AA426: =IF(Table2[[#This Row],[DeliveryDays]]<=3,"FAST DELIVERY","LATE DELIVERY") -> LATE DELIVERY | AB426: Consumer | AC426: Yes | AD426: 3 | AE426: =_xlfn.IFS(Table2[[#This Row],[Rating]]=5,"Excellent",Table2[[#This Row],[Rating]]=4,"Good",Table2[[#This Row],[Rating]]=3,"Average",Table2[[#This Row],[Rating]]<=2,"Poor") -> Average | AF426: =Table2[[#This Row],[Cost]]+Table2[[#This Row],[Profit]]+Table2[[#This Row],[ShippingCost]]+Table2[[#This Row],[DeliveryDays]] -> 6444.72 | AG426: =Table2[[#This Row],[Profit]]/Table2[[#This Row],[Cost]] -> 0.6865132 | AQ426: 983 | AR426: 2023-01-01 | AS426: Sara | AT426: East | AU426: India | AV426: New York | AW426: Electronics | AX426: Keyboard | AY426: Distributor | AZ426: Rep E | BA426: 277.76 | BB426: 18 | BC426: 0.05 | BD426: 4749.7 | BE426: 2745.82 | BF426: 2003.88 | BG426: PayPal | BH426: Critical | BI426: Standard | BJ426: 9.56 | BK426: 6 | BL426: Consumer | BM426: No | BN426: 1 | BO426: 12
A427: 426 | B427: 2024-07-14 | C427: =YEAR(Table2[[#This Row],[Date]]) -> 2024 | D427: =TEXT(Table2[[#This Row],[Date]],"mmmm") -> July | E427: Neha | F427: East | G427: UK | H427: New York | I427: Office Supplies | J427: Monitor | K427: Online | L427: Rep D | M427: 668.87 | N427: 13 | O427: 0.19 | P427: =IF(Table2[[#This Row],[Discount]]>20%,"HIGH","LOW") -> LOW | Q427: 7043.2 | R427: =_xlfn.IFS(Table2[[#This Row],[Revenue]]<1000,"Small",OR(Table2[[#This Row],[Revenue]]>1000,Table2[[#This Row],[Revenue]]<=5000),"Medium",Table2[[#This Row],[Revenue]]>5000,"Large") -> Medium | S427: =IF(Table2[[#This Row],[Revenue]]>3000,"Premium","Not Premium") -> Premium | T427: 5759.93 | U427: 1283.27 | V427: Credit Card | W427: Medium | X427: Express | Y427: 18.54 | Z427: 6 | AA427: =IF(Table2[[#This Row],[DeliveryDays]]<=3,"FAST DELIVERY","LATE DELIVERY") -> LATE DELIVERY | AB427: Home Office | AC427: No | AD427: 5 | AE427: =_xlfn.IFS(Table2[[#This Row],[Rating]]=5,"Excellent",Table2[[#This Row],[Rating]]=4,"Good",Table2[[#This Row],[Rating]]=3,"Average",Table2[[#This Row],[Rating]]<=2,"Poor") -> Excellent | AF427: =Table2[[#This Row],[Cost]]+Table2[[#This Row],[Profit]]+Table2[[#This Row],[ShippingCost]]+Table2[[#This Row],[DeliveryDays]] -> 7067.74 | AG427: =Table2[[#This Row],[Profit]]/Table2[[#This Row],[Cost]] -> 0.22279264 | AQ427: 996 | AR427: 2023-12-28 | AS427: David | AT427: West | AU427: India | AV427: Toronto | AW427: Sports | AX427: T-Shirt | AY427: Retail | AZ427: Rep B | BA427: 470.12 | BB427: 7 | BC427: 0.25 | BD427: 2468.13 | BE427: 1243.12 | BF427: 1225.01 | BG427: PayPal | BH427: Medium | BI427: Standard | BJ427: 28.08 | BK427: 5 | BL427: Corporate | BM427: No | BN427: 1
A428: 427 | B428: 2023-07-07 | C428: =YEAR(Table2[[#This Row],[Date]]) -> 2023 | D428: =TEXT(Table2[[#This Row],[Date]],"mmmm") -> July | E428: Michael | F428: North | G428: USA | H428: Mumbai | I428: Furniture | J428: Jacket | K428: Distributor | L428: Rep E | M428: 881.14 | N428: 17 | O428: 0.02 | P428: =IF(Table2[[#This Row],[Discount]]>20%,"HIGH","LOW") -> LOW | Q428: 14679.79 | R428: =_xlfn.IFS(Table2[[#This Row],[Revenue]]<1000,"Small",OR(Table2[[#This Row],[Revenue]]>1000,Table2[[#This Row],[Revenue]]<=5000),"Medium",Table2[[#This Row],[Revenue]]>5000,"Large") -> Medium | S428: =IF(Table2[[#This Row],[Revenue]]>3000,"Premium","Not Premium") -> Premium | T428: 10959.45 | U428: 3720.34 | V428: Credit Card | W428: Low | X428: Express | Y428: 18.22 | Z428: 5 | AA428: =IF(Table2[[#This Row],[DeliveryDays]]<=3,"FAST DELIVERY","LATE DELIVERY") -> LATE DELIVERY | AB428: Home Office | AC428: No | AD428: 2 | AE428: =_xlfn.IFS(Table2[[#This Row],[Rating]]=5,"Excellent",Table2[[#This Row],[Rating]]=4,"Good",Table2[[#This Row],[Rating]]=3,"Average",Table2[[#This Row],[Rating]]<=2,"Poor") -> Poor | AF428: =Table2[[#This Row],[Cost]]+Table2[[#This Row],[Profit]]+Table2[[#This Row],[ShippingCost]]+Table2[[#This Row],[DeliveryDays]] -> 14703.01 | AG428: =Table2[[#This Row],[Profit]]/Table2[[#This Row],[Cost]] -> 0.33946412
A429: 428 | B429: 2024-04-21 | C429: =YEAR(Table2[[#This Row],[Date]]) -> 2024 | D429: =TEXT(Table2[[#This Row],[Date]],"mmmm") -> April | E429: Priya | F429: North | G429: Germany | H429: London | I429: Clothing | J429: Monitor | K429: Distributor | L429: Rep E | M429: 126.87 | N429: 17 | O429: 0.24 | P429: =IF(Table2[[#This Row],[Discount]]>20%,"HIGH","LOW") -> HIGH | Q429: 1639.16 | R429: =_xlfn.IFS(Table2[[#This Row],[Revenue]]<1000,"Small",OR(Table2[[#This Row],[Revenue]]>1000,Table2[[#This Row],[Revenue]]<=5000),"Medium",Table2[[#This Row],[Revenue]]>5000,"Large") -> Medium | S429: =IF(Table2[[#This Row],[Revenue]]>3000,"Premium","Not Premium") -> Not Premium | T429: 1072.44 | U429: 566.72 | V429: Credit Card | W429: Critical | X429: Standard | Y429: 42.98 | Z429: 5 | AA429: =IF(Table2[[#This Row],[DeliveryDays]]<=3,"FAST DELIVERY","LATE DELIVERY") -> LATE DELIVERY | AB429: Consumer | AC429: Yes | AD429: 4 | AE429: =_xlfn.IFS(Table2[[#This Row],[Rating]]=5,"Excellent",Table2[[#This Row],[Rating]]=4,"Good",Table2[[#This Row],[Rating]]=3,"Average",Table2[[#This Row],[Rating]]<=2,"Poor") -> Good | AF429: =Table2[[#This Row],[Cost]]+Table2[[#This Row],[Profit]]+Table2[[#This Row],[ShippingCost]]+Table2[[#This Row],[DeliveryDays]] -> 1687.14 | AG429: =Table2[[#This Row],[Profit]]/Table2[[#This Row],[Cost]] -> 0.52843982
A430: 429 | B430: 2023-05-14 | C430: =YEAR(Table2[[#This Row],[Date]]) -> 2023 | D430: =TEXT(Table2[[#This Row],[Date]],"mmmm") -> May | E430: John | F430: East | G430: Germany | H430: Mumbai | I430: Clothing | J430: Chair | K430: Online | L430: Rep E | M430: 668.58 | N430: 13 | O430: 0.19 | P430: =IF(Table2[[#This Row],[Discount]]>20%,"HIGH","LOW") -> LOW | Q430: 7040.15 | R430: =_xlfn.IFS(Table2[[#This Row],[Revenue]]<1000,"Small",OR(Table2[[#This Row],[Revenue]]>1000,Table2[[#This Row],[Revenue]]<=5000),"Medium",Table2[[#This Row],[Revenue]]>5000,"Large") -> Medium | S430: =IF(Table2[[#This Row],[Revenue]]>3000,"Premium","Not Premium") -> Premium | T430: 4520.94 | U430: 2519.21 | V430: Credit Card | W430: Medium | X430: Express | Y430: 34.65 | Z430: 3 | AA430: =IF(Table2[[#This Row],[DeliveryDays]]<=3,"FAST DELIVERY","LATE DELIVERY") -> FAST DELIVERY | AB430: Corporate | AC430: No | AD430: 4 | AE430: =_xlfn.IFS(Table2[[#This Row],[Rating]]=5,"Excellent",Table2[[#This Row],[Rating]]=4,"Good",Table2[[#This Row],[Rating]]=3,"Average",Table2[[#This Row],[Rating]]<=2,"Poor") -> Good | AF430: =Table2[[#This Row],[Cost]]+Table2[[#This Row],[Profit]]+Table2[[#This Row],[ShippingCost]]+Table2[[#This Row],[DeliveryDays]] -> 7077.8 | AG430: =Table2[[#This Row],[Profit]]/Table2[[#This Row],[Cost]] -> 0.55723146
A431: 430 | B431: 2023-08-28 | C431: =YEAR(Table2[[#This Row],[Date]]) -> 2023 | D431: =TEXT(Table2[[#This Row],[Date]],"mmmm") -> August | E431: Michael | F431: North | G431: UK | H431: London | I431: Office Supplies | J431: Laptop | K431: Distributor | L431: Rep A | M431: 861.19 | N431: 17 | O431: 0.29 | P431: =IF(Table2[[#This Row],[Discount]]>20%,"HIGH","LOW") -> HIGH | Q431: 10394.56 | R431: =_xlfn.IFS(Table2[[#This Row],[Revenue]]<1000,"Small",OR(Table2[[#This Row],[Revenue]]>1000,Table2[[#This Row],[Revenue]]<=5000),"Medium",Table2[[#This Row],[Revenue]]>5000,"Large") -> Medium | S431: =IF(Table2[[#This Row],[Revenue]]>3000,"Premium","Not Premium") -> Premium | T431: 6602.78 | U431: 3791.78 | V431: Credit Card | W431: Medium | X431: Standard | Y431: 16.12 | Z431: 5 | AA431: =IF(Table2[[#This Row],[DeliveryDays]]<=3,"FAST DELIVERY","LATE DELIVERY") -> LATE DELIVERY | AB431: Home Office | AC431: Yes | AD431: 1 | AE431: =_xlfn.IFS(Table2[[#This Row],[Rating]]=5,"Excellent",Table2[[#This Row],[Rating]]=4,"Good",Table2[[#This Row],[Rating]]=3,"Average",Table2[[#This Row],[Rating]]<=2,"Poor") -> Poor | AF431: =Table2[[#This Row],[Cost]]+Table2[[#This Row],[Profit]]+Table2[[#This Row],[ShippingCost]]+Table2[[#This Row],[DeliveryDays]] -> 10415.68 | AG431: =Table2[[#This Row],[Profit]]/Table2[[#This Row],[Cost]] -> 0.57427023
A432: 431 | B432: 2024-01-23 | C432: =YEAR(Table2[[#This Row],[Date]]) -> 2024 | D432: =TEXT(Table2[[#This Row],[Date]],"mmmm") -> January | E432: Arjun | F432: South | G432: UK | H432: Pune | I432: Clothing | J432: T-Shirt | K432: Distributor | L432: Rep E | M432: 768.66 | N432: 15 | O432: 0.15 | P432: =IF(Table2[[#This Row],[Discount]]>20%,"HIGH","LOW") -> LOW | Q432: 9800.41 | R432: =_xlfn.IFS(Table2[[#This Row],[Revenue]]<1000,"Small",OR(Table2[[#This Row],[Revenue]]>1000,Table2[[#This Row],[Revenue]]<=5000),"Medium",Table2[[#This Row],[Revenue]]>5000,"Large") -> Medium | S432: =IF(Table2[[#This Row],[Revenue]]>3000,"Premium","Not Premium") -> Premium | T432: 4933.12 | U432: 4867.29 | V432: PayPal | W432: Critical | X432: Same Day | Y432: 25.41 | Z432: 6 | AA432: =IF(Table2[[#This Row],[DeliveryDays]]<=3,"FAST DELIVERY","LATE DELIVERY") -> LATE DELIVERY | AB432: Home Office | AC432: Yes | AD432: 2 | AE432: =_xlfn.IFS(Table2[[#This Row],[Rating]]=5,"Excellent",Table2[[#This Row],[Rating]]=4,"Good",Table2[[#This Row],[Rating]]=3,"Average",Table2[[#This Row],[Rating]]<=2,"Poor") -> Poor | AF432: =Table2[[#This Row],[Cost]]+Table2[[#This Row],[Profit]]+Table2[[#This Row],[ShippingCost]]+Table2[[#This Row],[DeliveryDays]] -> 9831.82 | AG432: =Table2[[#This Row],[Profit]]/Table2[[#This Row],[Cost]] -> 0.9866555
A433: 434 | B433: 2024-12-31 | C433: =YEAR(Table2[[#This Row],[Date]]) -> 2024 | D433: =TEXT(Table2[[#This Row],[Date]],"mmmm") -> December | E433: Rahul | F433: South | G433: India | H433: London | I433: Furniture | J433: T-Shirt | K433: Retail | L433: Rep A | M433: 177.77 | N433: 18 | O433: 0.04 | P433: =IF(Table2[[#This Row],[Discount]]>20%,"HIGH","LOW") -> LOW | Q433: 3071.87 | R433: =_xlfn.IFS(Table2[[#This Row],[Revenue]]<1000,"Small",OR(Table2[[#This Row],[Revenue]]>1000,Table2[[#This Row],[Revenue]]<=5000),"Medium",Table2[[#This Row],[Revenue]]>5000,"Large") -> Medium | S433: =IF(Table2[[#This Row],[Revenue]]>3000,"Premium","Not Premium") -> Premium | T433: 2039.73 | U433: 1032.14 | V433: Credit Card | W433: Medium | X433: Standard | Y433: 11.21 | Z433: 5 | AA433: =IF(Table2[[#This Row],[DeliveryDays]]<=3,"FAST DELIVERY","LATE DELIVERY") -> LATE DELIVERY | AB433: Home Office | AC433: Yes | AD433: 3 | AE433: =_xlfn.IFS(Table2[[#This Row],[Rating]]=5,"Excellent",Table2[[#This Row],[Rating]]=4,"Good",Table2[[#This Row],[Rating]]=3,"Average",Table2[[#This Row],[Rating]]<=2,"Poor") -> Average | AF433: =Table2[[#This Row],[Cost]]+Table2[[#This Row],[Profit]]+Table2[[#This Row],[ShippingCost]]+Table2[[#This Row],[DeliveryDays]] -> 3088.08 | AG433: =Table2[[#This Row],[Profit]]/Table2[[#This Row],[Cost]] -> 0.50601795
A434: 435 | B434: 2023-09-29 | C434: =YEAR(Table2[[#This Row],[Date]]) -> 2023 | D434: =TEXT(Table2[[#This Row],[Date]],"mmmm") -> September | E434: Neha | F434: East | G434: USA | H434: Pune | I434: Sports | J434: Laptop | K434: Retail | L434: Rep B | M434: 705.37 | N434: 20 | O434: 0.18 | P434: =IF(Table2[[#This Row],[Discount]]>20%,"HIGH","LOW") -> LOW | Q434: 11568.07 | R434: =_xlfn.IFS(Table2[[#This Row],[Revenue]]<1000,"Small",OR(Table2[[#This Row],[Revenue]]>1000,Table2[[#This Row],[Revenue]]<=5000),"Medium",Table2[[#This Row],[Revenue]]>5000,"Large") -> Medium | S434: =IF(Table2[[#This Row],[Revenue]]>3000,"Premium","Not Premium") -> Premium | T434: 8800.89 | U434: 2767.18 | V434: PayPal | W434: Medium | X434: Standard | Y434: 11.51 | Z434: 10 | AA434: =IF(Table2[[#This Row],[DeliveryDays]]<=3,"FAST DELIVERY","LATE DELIVERY") -> LATE DELIVERY | AB434: Consumer | AC434: No | AD434: 5 | AE434: =_xlfn.IFS(Table2[[#This Row],[Rating]]=5,"Excellent",Table2[[#This Row],[Rating]]=4,"Good",Table2[[#This Row],[Rating]]=3,"Average",Table2[[#This Row],[Rating]]<=2,"Poor") -> Excellent | AF434: =Table2[[#This Row],[Cost]]+Table2[[#This Row],[Profit]]+Table2[[#This Row],[ShippingCost]]+Table2[[#This Row],[DeliveryDays]] -> 11589.58 | AG434: =Table2[[#This Row],[Profit]]/Table2[[#This Row],[Cost]] -> 0.31442047
A435: 436 | B435: 2024-03-05 | C435: =YEAR(Table2[[#This Row],[Date]]) -> 2024 | D435: =TEXT(Table2[[#This Row],[Date]],"mmmm") -> March | E435: Sophia | F435: East | G435: Germany | H435: London | I435: Clothing | J435: Laptop | K435: Online | L435: Rep E | M435: 37.42 | N435: 20 | O435: 0.25 | P435: =IF(Table2[[#This Row],[Discount]]>20%,"HIGH","LOW") -> HIGH | Q435: 561.3 | R435: =_xlfn.IFS(Table2[[#This Row],[Revenue]]<1000,"Small",OR(Table2[[#This Row],[Revenue]]>1000,Table2[[#This Row],[Revenue]]<=5000),"Medium",Table2[[#This Row],[Revenue]]>5000,"Large") -> Small | S435: =IF(Table2[[#This Row],[Revenue]]>3000,"Premium","Not Premium") -> Not Premium | T435: 468.24 | U435: 93.06 | V435: PayPal | W435: Medium | X435: Express | Y435: 47.27 | Z435: 8 | AA435: =IF(Table2[[#This Row],[DeliveryDays]]<=3,"FAST DELIVERY","LATE DELIVERY") -> LATE DELIVERY | AB435: Corporate | AC435: No | AD435: 1 | AE435: =_xlfn.IFS(Table2[[#This Row],[Rating]]=5,"Excellent",Table2[[#This Row],[Rating]]=4,"Good",Table2[[#This Row],[Rating]]=3,"Average",Table2[[#This Row],[Rating]]<=2,"Poor") -> Poor | AF435: =Table2[[#This Row],[Cost]]+Table2[[#This Row],[Profit]]+Table2[[#This Row],[ShippingCost]]+Table2[[#This Row],[DeliveryDays]] -> 616.57 | AG435: =Table2[[#This Row],[Profit]]/Table2[[#This Row],[Cost]] -> 0.19874423
A436: 437 | B436: 2024-05-15 | C436: =YEAR(Table2[[#This Row],[Date]]) -> 2024 | D436: =TEXT(Table2[[#This Row],[Date]],"mmmm") -> May | E436: Sara | F436: South | G436: USA | H436: London | I436: Electronics | J436: Tablet | K436: Online | L436: Rep B | M436: 528.57 | N436: 18 | O436: 0.29 | P436: =IF(Table2[[#This Row],[Discount]]>20%,"HIGH","LOW") -> HIGH | Q436: 6755.12 | R436: =_xlfn.IFS(Table2[[#This Row],[Revenue]]<1000,"Small",OR(Table2[[#This Row],[Revenue]]>1000,Table2[[#This Row],[Revenue]]<=5000),"Medium",Table2[[#This Row],[Revenue]]>5000,"Large") -> Medium | S436: =IF(Table2[[#This Row],[Revenue]]>3000,"Premium","Not Premium") -> Premium | T436: 3507.51 | U436: 3247.61 | V436: Cash | W436: High | X436: Standard | Y436: 31.66 | Z436: 4 | AA436: =IF(Table2[[#This Row],[DeliveryDays]]<=3,"FAST DELIVERY","LATE DELIVERY") -> LATE DELIVERY | AB436: Consumer | AC436: No | AD436: 1 | AE436: =_xlfn.IFS(Table2[[#This Row],[Rating]]=5,"Excellent",Table2[[#This Row],[Rating]]=4,"Good",Table2[[#This Row],[Rating]]=3,"Average",Table2[[#This Row],[Rating]]<=2,"Poor") -> Poor | AF436: =Table2[[#This Row],[Cost]]+Table2[[#This Row],[Profit]]+Table2[[#This Row],[ShippingCost]]+Table2[[#This Row],[DeliveryDays]] -> 6790.78 | AG436: =Table2[[#This Row],[Profit]]/Table2[[#This Row],[Cost]] -> 0.92590185
A437: 438 | B437: 2024-09-03 | C437: =YEAR(Table2[[#This Row],[Date]]) -> 2024 | D437: =TEXT(Table2[[#This Row],[Date]],"mmmm") -> September | E437: Anita | F437: East | G437: USA | H437: Toronto | I437: Sports | J437: Monitor | K437: Retail | L437: Rep D | M437: 243.08 | N437: 6 | O437: 0.08 | P437: =IF(Table2[[#This Row],[Discount]]>20%,"HIGH","LOW") -> LOW | Q437: 1341.8 | R437: =_xlfn.IFS(Table2[[#This Row],[Revenue]]<1000,"Small",OR(Table2[[#This Row],[Revenue]]>1000,Table2[[#This Row],[Revenue]]<=5000),"Medium",Table2[[#This Row],[Revenue]]>5000,"Large") -> Medium | S437: =IF(Table2[[#This Row],[Revenue]]>3000,"Premium","Not Premium") -> Not Premium | T437: 693.12 | U437: 648.68 | V437: Credit Card | W437: Critical | X437: Same Day | Y437: 13.79 | Z437: 8 | AA437: =IF(Table2[[#This Row],[DeliveryDays]]<=3,"FAST DELIVERY","LATE DELIVERY") -> LATE DELIVERY | AB437: Consumer | AC437: Yes | AD437: 1 | AE437: =_xlfn.IFS(Table2[[#This Row],[Rating]]=5,"Excellent",Table2[[#This Row],[Rating]]=4,"Good",Table2[[#This Row],[Rating]]=3,"Average",Table2[[#This Row],[Rating]]<=2,"Poor") -> Poor | AF437: =Table2[[#This Row],[Cost]]+Table2[[#This Row],[Profit]]+Table2[[#This Row],[ShippingCost]]+Table2[[#This Row],[DeliveryDays]] -> 1363.59 | AG437: =Table2[[#This Row],[Profit]]/Table2[[#This Row],[Cost]] -> 0.93588412
A438: 439 | B438: 2023-07-26 | C438: =YEAR(Table2[[#This Row],[Date]]) -> 2023 | D438: =TEXT(Table2[[#This Row],[Date]],"mmmm") -> July | E438: Arjun | F438: South | G438: Australia | H438: Berlin | I438: Furniture | J438: Football | K438: Distributor | L438: Rep D | M438: 821.97 | N438: 10 | O438: 0.22 | P438: =IF(Table2[[#This Row],[Discount]]>20%,"HIGH","LOW") -> HIGH | Q438: 6411.37 | R438: =_xlfn.IFS(Table2[[#This Row],[Revenue]]<1000,"Small",OR(Table2[[#This Row],[Revenue]]>1000,Table2[[#This Row],[Revenue]]<=5000),"Medium",Table2[[#This Row],[Revenue]]>5000,"Large") -> Medium | S438: =IF(Table2[[#This Row],[Revenue]]>3000,"Premium","Not Premium") -> Premium | T438: 3920.33 | U438: 2491.04 | V438: PayPal | W438: Critical | X438: Same Day | Y438: 42.29 | Z438: 7 | AA438: =IF(Table2[[#This Row],[DeliveryDays]]<=3,"FAST DELIVERY","LATE DELIVERY") -> LATE DELIVERY | AB438: Home Office | AC438: No | AD438: 5 | AE438: =_xlfn.IFS(Table2[[#This Row],[Rating]]=5,"Excellent",Table2[[#This Row],[Rating]]=4,"Good",Table2[[#This Row],[Rating]]=3,"Average",Table2[[#This Row],[Rating]]<=2,"Poor") -> Excellent | AF438: =Table2[[#This Row],[Cost]]+Table2[[#This Row],[Profit]]+Table2[[#This Row],[ShippingCost]]+Table2[[#This Row],[DeliveryDays]] -> 6460.66 | AG438: =Table2[[#This Row],[Profit]]/Table2[[#This Row],[Cost]] -> 0.6354159
A439: 440 | B439: 2024-09-09 | C439: =YEAR(Table2[[#This Row],[Date]]) -> 2024 | D439: =TEXT(Table2[[#This Row],[Date]],"mmmm") -> September | E439: Riya | F439: East | G439: Canada | H439: Berlin | I439: Electronics | J439: Monitor | K439: Online | L439: Rep C | M439: 829.29 | N439: 17 | O439: 0.09 | P439: =IF(Table2[[#This Row],[Discount]]>20%,"HIGH","LOW") -> LOW | Q439: 12829.12 | R439: =_xlfn.IFS(Table2[[#This Row],[Revenue]]<1000,"Small",OR(Table2[[#This Row],[Revenue]]>1000,Table2[[#This Row],[Revenue]]<=5000),"Medium",Table2[[#This Row],[Revenue]]>5000,"Large") -> Medium | S439: =IF(Table2[[#This Row],[Revenue]]>3000,"Premium","Not Premium") -> Premium | T439: 6806.6 | U439: 6022.52 | V439: Credit Card | W439: Low | X439: Express | Y439: 43.75 | Z439: 9 | AA439: =IF(Table2[[#This Row],[DeliveryDays]]<=3,"FAST DELIVERY","LATE DELIVERY") -> LATE DELIVERY | AB439: Consumer | AC439: Yes | AD439: 5 | AE439: =_xlfn.IFS(Table2[[#This Row],[Rating]]=5,"Excellent",Table2[[#This Row],[Rating]]=4,"Good",Table2[[#This Row],[Rating]]=3,"Average",Table2[[#This Row],[Rating]]<=2,"Poor") -> Excellent | AF439: =Table2[[#This Row],[Cost]]+Table2[[#This Row],[Profit]]+Table2[[#This Row],[ShippingCost]]+Table2[[#This Row],[DeliveryDays]] -> 12881.87 | AG439: =Table2[[#This Row],[Profit]]/Table2[[#This Row],[Cost]] -> 0.88480592
... A999: 1000 | B999: 2024-01-28 | C999: =YEAR(Table2[[#This Row],[Date]]) -> 2024 | D999: =TEXT(Table2[[#This Row],[Date]],"mmmm") -> January | E999: John | F999: West | G999: Canada | H999: Berlin | I999: Clothing | J999: Monitor | K999: Retail | L999: Rep B | M999: 728.32 | N999: 19 | O999: 0.25 | P999: =IF(Table2[[#This Row],[Discount]]>20%,"HIGH","LOW") -> HIGH | Q999: 10378.56 | R999: =_xlfn.IFS(Table2[[#This Row],[Revenue]]<1000,"Small",OR(Table2[[#This Row],[Revenue]]>1000,Table2[[#This Row],[Revenue]]<=5000),"Medium",Table2[[#This Row],[Revenue]]>5000,"Large") -> Medium | S999: =IF(Table2[[#This Row],[Revenue]]>3000,"Premium","Not Premium") -> Premium | T999: 6524.32 | U999: 3854.24 | V999: Cash | W999: High | X999: Same Day | Y999: 18.53 | Z999: 7 | AA999: =IF(Table2[[#This Row],[DeliveryDays]]<=3,"FAST DELIVERY","LATE DELIVERY") -> LATE DELIVERY | AB999: Consumer | AC999: Yes | AD999: 4 | AE999: =_xlfn.IFS(Table2[[#This Row],[Rating]]=5,"Excellent",Table2[[#This Row],[Rating]]=4,"Good",Table2[[#This Row],[Rating]]=3,"Average",Table2[[#This Row],[Rating]]<=2,"Poor") -> Good | AF999: =Table2[[#This Row],[Cost]]+Table2[[#This Row],[Profit]]+Table2[[#This Row],[ShippingCost]]+Table2[[#This Row],[DeliveryDays]] -> 10404.09 | AG999: =Table2[[#This Row],[Profit]]/Table2[[#This Row],[Cost]] -> 0.59074969
AJ1070: Show orders with Rating = 5.
AJ1071: Rating
AJ1072: 5
AJ1074: OrderID | AK1074: Date | AL1074: CustomerName | AM1074: Region | AN1074: Country | AO1074: City | AP1074: ProductCategory | AQ1074: ProductName | AR1074: SalesChannel | AS1074: SalesRep | AT1074: UnitPrice | AU1074: Quantity | AV1074: Discount | AW1074: Revenue | AX1074: Cost | AY1074: Profit | AZ1074: PaymentMethod | BA1074: OrderPriority | BB1074: ShipMode | BC1074: ShippingCost | BD1074: DeliveryDays | BE1074: CustomerSegment | BF1074: Returned | BG1074: Rating | BH1074: Month
AJ1075: 19 | AK1075: 2024-12-27 | AL1075: Sara | AM1075: East | AN1075: USA | AO1075: Mumbai | AP1075: Electronics | AQ1075: Printer | AR1075: Distributor | AS1075: Rep C | AT1075: 592.47 | AU1075: 19 | AV1075: 0.08 | AW1075: 10356.38 | AX1075: 8696.16 | AY1075: 1660.22 | AZ1075: PayPal | BA1075: Critical | BB1075: Standard | BC1075: 16.1 | BD1075: 3 | BE1075: Consumer | BF1075: Yes | BG1075: 5 | BH1075: 12
AJ1076: 25 | AK1076: 2024-08-24 | AL1076: Priya | AM1076: South | AN1076: Germany | AO1076: Delhi | AP1076: Electronics | AQ1076: T-Shirt | AR1076: Retail | AS1076: Rep B | AT1076: 823.06 | AU1076: 6 | AV1076: 0.1 | AW1076: 4444.52 | AX1076: 3447.91 | AY1076: 996.61 | AZ1076: PayPal | BA1076: Medium | BB1076: Express | BC1076: 10.2 | BD1076: 1 | BE1076: Consumer | BF1076: Yes | BG1076: 5 | BH1076: 8
AJ1077: 27 | AK1077: 2023-04-27 | AL1077: Arjun | AM1077: North | AN1077: India | AO1077: New York | AP1077: Electronics | AQ1077: Football | AR1077: Online | AS1077: Rep E | AT1077: 600.43 | AU1077: 17 | AV1077: 0.17 | AW1077: 8472.07 | AX1077: 4854.92 | AY1077: 3617.15 | AZ1077: Credit Card | BA1077: Low | BB1077: Same Day | BC1077: 12.96 | BD1077: 6 | BE1077: Home Office | BF1077: Yes | BG1077: 5 | BH1077: 4
AJ1078: 28 | AK1078: 2023-05-19 | AL1078: Amit | AM1078: North | AN1078: India | AO1078: Toronto | AP1078: Electronics | AQ1078: T-Shirt | AR1078: Retail | AS1078: Rep D | AT1078: 697.99 | AU1078: 7 | AV1078: 0.1 | AW1078: 4397.34 | AX1078: 2823.58 | AY1078: 1573.76 | AZ1078: UPI | BA1078: Critical | BB1078: Same Day | BC1078: 27.37 | BD1078: 1 | BE1078: Consumer | BF1078: Yes | BG1078: 5 | BH1078: 5
AJ1079: 30 | AK1079: 2023-04-09 | AL1079: Anita | AM1079: East | AN1079: India | AO1079: Mumbai | AP1079: Furniture | AQ1079: T-Shirt | AR1079: Online | AS1079: Rep E | AT1079: 471.7 | AU1079: 14 | AV1079: 0.27 | AW1079: 4820.77 | AX1079: 3546.14 | AY1079: 1274.63 | AZ1079: Bank Transfer | BA1079: Medium | BB1079: Express | BC1079: 29.81 | BD1079: 2 | BE1079: Consumer | BF1079: No | BG1079: 5 | BH1079: 4
AJ1080: 32 | AK1080: 2023-03-27 | AL1080: Amit | AM1080: West | AN1080: UK | AO1080: Toronto | AP1080: Clothing | AQ1080: Laptop | AR1080: Retail | AS1080: Rep B | AT1080: 108.96 | AU1080: 14 | AV1080: 0.14 | AW1080: 1311.88 | AX1080: 872.57 | AY1080: 439.31 | AZ1080: Credit Card | BA1080: Low | BB1080: Standard | BC1080: 14.45 | BD1080: 2 | BE1080: Consumer | BF1080: No | BG1080: 5 | BH1080: 3
AJ1081: 33 | AK1081: 2024-03-16 | AL1081: Arjun | AM1081: West | AN1081: India | AO1081: New York | AP1081: Furniture | AQ1081: Jacket | AR1081: Distributor | AS1081: Rep D | AT1081: 103.94 | AU1081: 4 | AV1081: 0.15 | AW1081: 353.4 | AX1081: 206.51 | AY1081: 146.89 | AZ1081: Credit Card | BA1081: Low | BB1081: Same Day | BC1081: 29.93 | BD1081: 3 | BE1081: Corporate | BF1081: Yes | BG1081: 5 | BH1081: 3
AJ1082: 37 | AK1082: 2024-05-02 | AL1082: Arjun | AM1082: South | AN1082: USA | AO1082: Delhi | AP1082: Electronics | AQ1082: T-Shirt | AR1082: Retail | AS1082: Rep D | AT1082: 423.11 | AU1082: 20 | AV1082: 0.23 | AW1082: 6515.89 | AX1082: 4640.04 | AY1082: 1875.85 | AZ1082: Cash | BA1082: Medium | BB1082: Same Day | BC1082: 31.13 | BD1082: 8 | BE1082: Home Office | BF1082: No | BG1082: 5 | BH1082: 5
AJ1083: 43 | AK1083: 2024-12-16 | AL1083: Arjun | AM1083: South | AN1083: Germany | AO1083: New York | AP1083: Electronics | AQ1083: Monitor | AR1083: Online | AS1083: Rep E | AT1083: 854.24 | AU1083: 2 | AV1083: 0.14 | AW1083: 1469.29 | AX1083: 1206.28 | AY1083: 263.01 | AZ1083: PayPal | BA1083: Critical | BB1083: Express | BC1083: 25.79 | BD1083: 9 | BE1083: Home Office | BF1083: No | BG1083: 5 | BH1083: 12
AJ1084: 54 | AK1084: 2024-03-17 | AL1084: Rahul | AM1084: South | AN1084: India | AO1084: Pune | AP1084: Electronics | AQ1084: Football | AR1084: Online | AS1084: Rep A | AT1084: 288.68 | AU1084: 2 | AV1084: 0.02 | AW1084: 565.81 | AX1084: 451.49 | AY1084: 114.32 | AZ1084: Bank Transfer | BA1084: High | BB1084: Standard | BC1084: 36.45 | BD1084: 7 | BE1084: Home Office | BF1084: Yes | BG1084: 5 | BH1084: 3
AJ1085: 55 | AK1085: 2024-05-06 | AL1085: Sara | AM1085: North | AN1085: Germany | AO1085: Sydney | AP1085: Furniture | AQ1085: Desk | AR1085: Online | AS1085: Rep C | AT1085: 112.94 | AU1085: 4 | AV1085: 0.18 | AW1085: 370.44 | AX1085: 219.05 | AY1085: 151.39 | AZ1085: PayPal | BA1085: Low | BB1085: Express | BC1085: 9.18 | BD1085: 7 | BE1085: Corporate | BF1085: No | BG1085: 5 | BH1085: 5
AJ1086: 59 | AK1086: 2023-04-10 | AL1086: David | AM1086: South | AN1086: UK | AO1086: Toronto | AP1086: Clothing | AQ1086: Football | AR1086: Retail | AS1086: Rep C | AT1086: 974.86 | AU1086: 14 | AV1086: 0.17 | AW1086: 11327.87 | AX1086: 5832.16 | AY1086: 5495.71 | AZ1086: Bank Transfer | BA1086: High | BB1086: Same Day | BC1086: 31.05 | BD1086: 5 | BE1086: Home Office | BF1086: Yes | BG1086: 5 | BH1086: 4
... AJ1271: 999 | AK1271: 2024-06-04 | AL1271: Sara | AM1271: South | AN1271: Canada | AO1271: Berlin | AP1271: Office Supplies | AQ1271: Tablet | AR1271: Online | AS1271: Rep C | AT1271: 120.97 | AU1271: 12 | AV1271: 0.13 | AW1271: 1262.93 | AX1271: 794.93 | AY1271: 468 | AZ1271: PayPal | BA1271: Medium | BB1271: Express | BC1271: 39.05 | BD1271: 3 | BE1271: Corporate | BF1271: No | BG1271: 5 | BH1271: 6
...

Sheet PivotTable
A1: Pivot: Revenue by Region. | F1: Pivot: Revenue by Country. | J1: Pivot: Revenue by Product Category. | O1: Pivot: Profit by Product Category. | U1: Pivot: Revenue by Region & Category. | Y1: Pivot: Profit by SalesRep. | AE1: Pivot: Quantity by ProductName. | AK1: Pivot: Revenue by Month. | AP1: Pivot: Revenue by Customer Segment. | AU1: Create Line Chart – Monthly Sales Trend. | BB1: Create Pie Chart – Sales by Region. | BI1: Create Bar Chart – Top 10 Products.
A3: Row Labels | B3: Sum of Revenue | F3: Row Labels | G3: Sum of Revenue | J3: Row Labels | K3: Sum of Revenue | O3: Row Labels | P3: Sum of Profit | U3: Row Labels | V3: Sum of Revenue | Y3: Row Labels | Z3: Sum of Revenue | AE3: Row Labels | AF3: Sum of Quantity | AK3: Row Labels | AL3: Sum of Revenue | AP3: Row Labels | AQ3: Sum of Revenue | AU3: Row Labels | AV3: Sum of SaleValue | BB3: Row Labels | BC3: Sum of SaleValue | BI3: Row Labels | BJ3: Sum of Revenue
A4: East | B4: 1110336.3 | F4: India | G4: 838241.26 | J4: Sports | K4: 917606.1 | O4: Sports | P4: 286724.31 | U4: East | V4: 1110336.3 | Y4: Rep A | Z4: 1068802.7 | AE4: Chair | AF4: 1048 | AK4: January | AL4: 305092.44 | AP4: Amit | AQ4: 306286.38 | AU4: January | AV4: 307506.98 | BB4: East | BC4: 1118934.7 | BI4: Chair | BJ4: 442164.87
A5: North | B5: 1197873.4 | F5: Canada | G5: 728704.31 | J5: Electronics | K5: 902960.05 | O5: Electronics | P5: 284158.77 | U5: Sports | V5: 227045.07 | Y5: Rep B | Z5: 786462.15 | AE5: Desk | AF5: 975 | AK5: February | AL5: 324240.36 | AP5: Anita | AQ5: 224648.93 | AU5: February | AV5: 326483.54 | BB5: North | BC5: 1206003.1 | BI5: Desk | BJ5: 427092.37
A6: South | B6: 1166982.6 | F6: Australia | G6: 594630.68 | J6: Clothing | K6: 958416.66 | O6: Clothing | P6: 289105.52 | U6: Electronics | V6: 273275.36 | Y6: Rep C | Z6: 763111.79 | AE6: Football | AF6: 997 | AK6: March | AL6: 345517.57 | AP6: Arjun | AQ6: 436831.05 | AU6: March | AV6: 348582.49 | BB6: South | BC6: 1175761.3 | BI6: Football | BJ6: 418704
A7: West | B7: 925600.88 | F7: Germany | G7: 707480.65 | J7: Furniture | K7: 786187.66 | O7: Furniture | P7: 231549.59 | U7: Clothing | V7: 234925.62 | Y7: Rep D | Z7: 906495.67 | AE7: Jacket | AF7: 1085 | AK7: April | AL7: 245976.51 | AP7: David | AQ7: 386313.6 | AU7: April | AV7: 248734.52 | BB7: West | BC7: 933209.99 | BI7: Jacket | BJ7: 483091.29
A8: Grand Total | B8: 4400793.2 | F8: UK | G8: 761552.3 | J8: Office Supplies | K8: 835622.72 | O8: Office Supplies | P8: 240020.33 | U8: Furniture | V8: 155221.4 | Y8: Rep E | Z8: 875920.93 | AE8: Keyboard | AF8: 1096 | AK8: May | AL8: 463426.5 | AP8: John | AQ8: 337138.62 | AU8: May | AV8: 466286.82 | BB8: Grand Total | BC8: 4433909.1 | BI8: Keyboard | BJ8: 482773.78
F9: USA | G9: 770183.99 | J9: Grand Total | K9: 4400793.2 | O9: Grand Total | P9: 1331558.5 | U9: Office Supplies | V9: 219868.86 | Y9: Grand Total | Z9: 4400793.2 | AE9: Laptop | AF9: 1220 | AK9: June | AL9: 323348.37 | AP9: Michael | AQ9: 380840.59 | AU9: June | AV9: 326385.37 | BI9: Laptop | BJ9: 459859.57
F10: Grand Total | G10: 4400793.2 | U10: North | V10: 1197873.4 | AE10: Monitor | AF10: 989 | AK10: July | AL10: 478422.08 | AP10: Neha | AQ10: 405933.01 | AU10: July | AV10: 481599.27 | BI10: Monitor | BJ10: 384473.42
I11: Create Column Chart – Revenue by Category. | U11: Sports | V11: 226664.2 | AE11: Printer | AF11: 928 | AK11: August | AL11: 375497.65 | AP11: Priya | AQ11: 441565.8 | AU11: August | AV11: 377733.91 | BI11: Printer | BJ11: 388207.91
U12: Electronics | V12: 262475.37 | AE12: Tablet | AF12: 913 | AK12: September | AL12: 398941.79 | AP12: Rahul | AQ12: 354356.14 | AU12: September | AV12: 401921.06 | BI12: Tablet | BJ12: 371187.8
U13: Clothing | V13: 300358.86 | AE13: T-Shirt | AF13: 1227 | AK13: October | AL13: 397456.12 | AP13: Riya | AQ13: 355436.56 | AU13: October | AV13: 400276.68 | BI13: T-Shirt | BJ13: 543238.18
U14: Furniture | V14: 202488.73 | AE14: Grand Total | AF14: 10478 | AK14: November | AL14: 298662.64 | AP14: Sara | AQ14: 352665.12 | AU14: November | AV14: 300850.43 | BI14: Grand Total | BJ14: 4400793.2
U15: Office Supplies | V15: 205886.26 | AK15: December | AL15: 444211.16 | AP15: Sophia | AQ15: 418777.39 | AU15: December | AV15: 447548.01
U16: South | V16: 1166982.6 | AK16: Grand Total | AL16: 4400793.2 | AP16: Grand Total | AQ16: 4400793.2 | AU16: Grand Total | AV16: 4433909.1
U17: Sports | V17: 225771.9
U18: Electronics | V18: 194728.82
U19: Clothing | V19: 230950.21
U20: Furniture | V20: 262875.1
U21: Office Supplies | V21: 252656.55
U22: West | V22: 925600.88
U23: Sports | V23: 238124.93
U24: Electronics | V24: 172480.5
U25: Clothing | V25: 192181.97
U26: Furniture | V26: 165602.43
U27: Office Supplies | V27: 157211.05
U28: Grand Total | V28: 4400793.2
S31: Create Stacked Chart – Revenue by Region & Category.

Sheet Question
A1: 1. Basic Excel Questions (Formulas & Simple Analysis) Counting & Basic Stats | M1: Filtering Practice
A2: Count total number of orders. Count how many customers appear in the dataset. Count orders where Returned = Yes. Count orders where Returned = No. Find the average UnitPrice. Find the maximum UnitPrice. Find the minimum UnitPrice. Find average Quantity sold per order. Find maximum Quantity sold. Find minimum Quantity sold. Basic Sales Calculations Calculate Total Revenue. Calculate Total Cost. Calculate Total Profit. Calculate Average Profit per Order. Calculate Average Revenue per Order. Filtering Practice Show only Electronics products. Show only orders from India. Show orders with Discount greater than 10%. Show orders with Rating = 5. Show orders from Online sales channel. | M2: Show only Electronics products. Show only orders from India. Show orders with Discount greater than 10%. Show orders with Rating = 5. Show orders from Online sales channel.M12:V12
M12: 2. Sorting & Filtering Questions
M13: Sort orders by Revenue (Highest to Lowest). Sort by Date (Oldest to Newest). Sort by Profit descending. Find Top 10 highest revenue orders. Find Top 10 highest profit orders.
M23: Conditional Filtering
M24: Orders where Profit < 0. Orders where Discount > 20%. Orders where ShippingCost > 40. Orders where DeliveryDays > 7. Orders where Priority = Critical.
M37: 3. Conditional Formatting Questions
M38: Highlight Revenue greater than 5000. Highlight Profit less than 0. Highlight Returned = Yes. Highlight Top 10 highest profit orders. Highlight Rating below 3.
M49: 4. Logical Formula Questions (IF / AND / OR)
M50: Create column High Discount if Discount > 20%. Create column Loss Order if Profit < 0. Create column Fast Delivery if DeliveryDays ≤ 3. Create column Late Delivery if DeliveryDays > 7. Create column Premium Order if Revenue > 3000.
A55: Basic Sales Calculations
A56: Calculate Total Revenue. Calculate Total Cost. Calculate Total Profit. Calculate Average Profit per Order. Calculate Average Revenue per Order.
M61: Nested IF
M62: Categorize Rating: 5 = Excellent 4 = Good 3 = Average 1–2 = Poor Categorize Order Size: Small (<1000 revenue) Medium (1000–5000) Large (>5000)
A72: 5. Lookup Function Questions VLOOKUP
A73: Lookup Product Category using Product Name. Lookup SalesRep for an OrderID. Lookup Country using City.
A81: XLOOKUP / INDEX MATCH | M81: Aggregation Questions (SUMIFS / COUNTIFS)
A82: Find Revenue for a specific OrderID. Find CustomerName for highest revenue order. Find Product with highest quantity sold. Find Region for a given CustomerName. Find Payment method for a specific order. | M82: Total Revenue for Electronics. Total Revenue for Furniture. Total Revenue for India. Total Revenue for Online channel. Total Profit for West region. Multiple Criteria Revenue where Region = North AND Category = Electronics. Count orders where Rating = 5 AND Returned = No. Count orders where Priority = High AND Region = South. Profit where Discount > 20%. Revenue where PaymentMethod = Credit Card.
A93: Date & Time Analysis
A94: Extract Year from Date. Extract Month Name from Date. Count orders per Month. Calculate Revenue per Month. Find Month with highest revenue.
M100: Multiple Criteria
M101: Revenue where Region = North AND Category = Electronics. Count orders where Rating = 5 AND ReturRevenue where Region = North AND Category = Electronics. Count orders where Rating = 5 AND Returned = No. Count orders where Priority = High AND Region = South. Profit where Discount > 20%. Revenue where PaymentMethod = Credit Card.ned = No. Count orders where Priority = High AND Region = South. Profit where Discount > 20%. Revenue where PaymentMethod = Credit Card.
A104: Time Trends
A105: Create Monthly Sales Trend. Create Monthly Profit Trend. Find best performing month. Find worst performing month. Calculate monthly growth rate
M116: Pivot Table Questions
A117: Advanced Pivot | M117: Pivot: Revenue by Region. Pivot: Revenue by Country. Pivot: Revenue by Product Category. Pivot: Profit by Product Category. Pivot: Orders by Sales Channel.
A118: Pivot: Revenue by Region & Category. Pivot: Profit by SalesRep. Pivot: Quantity by ProductName. Pivot: Revenue by Month. Pivot: Revenue by Customer Segment.
A130: Chart Questions | M130: Profitability Analysis
A131: Create Column Chart – Revenue by Category. Create Line Chart – Monthly Sales Trend. Create Pie Chart – Sales by Region. Create Bar Chart – Top 10 Products. Create Stacked Chart – Revenue by Region & Category. | M131: Calculate profit margin per order. Identify lowest profit margin product. Identify highest profit margin product. Find products causing most losses. Find most profitable region.
